{"2230059":{"code":"14109","old_zip_code":"223","zip_code":"2230059","pref_kana":"ｶﾅｶﾞﾜｹﾝ","city_kana":"ﾖｺﾊﾏｼｺｳﾎｸｸ","town_kana":"ｷﾀｼﾝﾖｺﾊﾏ","pref_kanji":"神奈川県","city_kanji":"横浜市港北区","town_kanji":"北新横浜","pref_roman":"KANAGAWA KEN","city_roman":"YOKOHAMA SHI KOHOKU KU","town_roman":"KITASHINYOKOHAMA"},"2230064":{"code":"14109","old_zip_code":"223","zip_code":"2230064","pref_kana":"ｶﾅｶﾞﾜｹﾝ","city_kana":"ﾖｺﾊﾏｼｺｳﾎｸｸ","town_kana":"ｼﾓﾀﾞﾁｮｳ","pref_kanji":"神奈川県","city_kanji":"横浜市港北区","town_kanji":"下田町","pref_roman":"KANAGAWA KEN","city_roman":"YOKOHAMA SHI KOHOKU KU","town_roman":"SHIMODACHO"},"2230056":{"code":"14109","old_zip_code":"223","zip_code":"2230056","pref_kana":"ｶﾅｶﾞﾜｹﾝ","city_kana":"ﾖｺﾊﾏｼｺｳﾎｸｸ","town_kana":"ｼﾝﾖｼﾀﾞﾁｮｳ","pref_kanji":"神奈川県","city_kanji":"横浜市港北区","town_kanji":"新吉田町","pref_roman":"KANAGAWA KEN","city_roman":"YOKOHAMA SHI KOHOKU KU","town_roman":"SHINYOSHIDACHO"},"2230058":{"code":"14109","old_zip_code":"223","zip_code":"2230058","pref_kana":"ｶﾅｶﾞﾜｹﾝ","city_kana":"ﾖｺﾊﾏｼｺｳﾎｸｸ","town_kana":"ｼﾝﾖｼﾀﾞﾋｶﾞｼ","pref_kanji":"神奈川県","city_kanji":"横浜市港北区","town_kanji":"新吉田東","pref_roman":"KANAGAWA KEN","city_roman":"YOKOHAMA SHI KOHOKU KU","town_roman":"SHINYOSHIDAHIGASHI"},"2230063":{"code":"14109","old_zip_code":"223","zip_code":"2230063","pref_kana":"ｶﾅｶﾞﾜｹﾝ","city_kana":"ﾖｺﾊﾏｼｺｳﾎｸｸ","town_kana":"ﾀｶﾀﾁｮｳ","pref_kanji":"神奈川県","city_kanji":"横浜市港北区","town_kanji":"高田町","pref_roman":"KANAGAWA KEN","city_roman":"YOKOHAMA SHI KOHOKU KU","town_roman":"TAKATACHO"},"2230066":{"code":"14109","old_zip_code":"223","zip_code":"2230066","pref_kana":"ｶﾅｶﾞﾜｹﾝ","city_kana":"ﾖｺﾊﾏｼｺｳﾎｸｸ","town_kana":"ﾀｶﾀﾆｼ","pref_kanji":"神奈川県","city_kanji":"横浜市港北区","town_kanji":"高田西","pref_roman":"KANAGAWA KEN","city_roman":"YOKOHAMA SHI KOHOKU KU","town_roman":"TAKATANISHI"},"2230065":{"code":"14109","old_zip_code":"223","zip_code":"2230065","pref_kana":"ｶﾅｶﾞﾜｹﾝ","city_kana":"ﾖｺﾊﾏｼｺｳﾎｸｸ","town_kana":"ﾀｶﾀﾋｶﾞｼ","pref_kanji":"神奈川県","city_kanji":"横浜市港北区","town_kanji":"高田東","pref_roman":"KANAGAWA KEN","city_roman":"YOKOHAMA SHI KOHOKU KU","town_roman":"TAKATAHIGASHI"},"2230055":{"code":"14109","old_zip_code":"223","zip_code":"2230055","pref_kana":"ｶﾅｶﾞﾜｹﾝ","city_kana":"ﾖｺﾊﾏｼｺｳﾎｸｸ","town_kana":"ﾂﾅｼﾏｶﾐﾁｮｳ","pref_kanji":"神奈川県","city_kanji":"横浜市港北区","town_kanji":"綱島上町","pref_roman":"KANAGAWA KEN","city_roman":"YOKOHAMA SHI KOHOKU KU","town_roman":"TSUNASHIMAKAMICHO"},"2230054":{"code":"14109","old_zip_code":"223","zip_code":"2230054","pref_kana":"ｶﾅｶﾞﾜｹﾝ","city_kana":"ﾖｺﾊﾏｼｺｳﾎｸｸ","town_kana":"ﾂﾅｼﾏﾀﾞｲ","pref_kanji":"神奈川県","city_kanji":"横浜市港北区","town_kanji":"綱島台","pref_roman":"KANAGAWA KEN","city_roman":"YOKOHAMA SHI KOHOKU KU","town_roman":"TSUNASHIMADAI"},"2230052":{"code":"14109","old_zip_code":"223","zip_code":"2230052","pref_kana":"ｶﾅｶﾞﾜｹﾝ","city_kana":"ﾖｺﾊﾏｼｺｳﾎｸｸ","town_kana":"ﾂﾅｼﾏﾋｶﾞｼ","pref_kanji":"神奈川県","city_kanji":"横浜市港北区","town_kanji":"綱島東","pref_roman":"KANAGAWA KEN","city_roman":"YOKOHAMA SHI KOHOKU KU","town_roman":"TSUNASHIMAHIGASHI"},"2230053":{"code":"14109","old_zip_code":"223","zip_code":"2230053","pref_kana":"ｶﾅｶﾞﾜｹﾝ","city_kana":"ﾖｺﾊﾏｼｺｳﾎｸｸ","town_kana":"ﾂﾅｼﾏﾆｼ","pref_kanji":"神奈川県","city_kanji":"横浜市港北区","town_kanji":"綱島西","pref_roman":"KANAGAWA KEN","city_roman":"YOKOHAMA SHI KOHOKU KU","town_roman":"TSUNASHIMANISHI"},"2230057":{"code":"14109","old_zip_code":"223","zip_code":"2230057","pref_kana":"ｶﾅｶﾞﾜｹﾝ","city_kana":"ﾖｺﾊﾏｼｺｳﾎｸｸ","town_kana":"ﾆｯﾊﾟﾁｮｳ","pref_kanji":"神奈川県","city_kanji":"横浜市港北区","town_kanji":"新羽町","pref_roman":"KANAGAWA KEN","city_roman":"YOKOHAMA SHI KOHOKU KU","town_roman":"NIPPACHO"},"2230061":{"code":"14109","old_zip_code":"223","zip_code":"2230061","pref_kana":"ｶﾅｶﾞﾜｹﾝ","city_kana":"ﾖｺﾊﾏｼｺｳﾎｸｸ","town_kana":"ﾋﾖｼ","pref_kanji":"神奈川県","city_kanji":"横浜市港北区","town_kanji":"日吉","pref_roman":"KANAGAWA KEN","city_roman":"YOKOHAMA SHI KOHOKU KU","town_roman":"HIYOSHI"},"2230062":{"code":"14109","old_zip_code":"223","zip_code":"2230062","pref_kana":"ｶﾅｶﾞﾜｹﾝ","city_kana":"ﾖｺﾊﾏｼｺｳﾎｸｸ","town_kana":"ﾋﾖｼﾎﾝﾁｮｳ","pref_kanji":"神奈川県","city_kanji":"横浜市港北区","town_kanji":"日吉本町","pref_roman":"KANAGAWA KEN","city_roman":"YOKOHAMA SHI KOHOKU KU","town_roman":"HIYOSHIHONCHO"},"2230051":{"code":"14109","old_zip_code":"223","zip_code":"2230051","pref_kana":"ｶﾅｶﾞﾜｹﾝ","city_kana":"ﾖｺﾊﾏｼｺｳﾎｸｸ","town_kana":"ﾐﾉﾜﾁｮｳ","pref_kanji":"神奈川県","city_kanji":"横浜市港北区","town_kanji":"箕輪町","pref_roman":"KANAGAWA KEN","city_roman":"YOKOHAMA SHI KOHOKU KU","town_roman":"MINOWACHO"}}
