{"2991100":{"code":"12225","old_zip_code":"29911","zip_code":"2991100","pref_kana":"ﾁﾊﾞｹﾝ","city_kana":"ｷﾐﾂｼ","town_kana":"","pref_kanji":"千葉県","city_kanji":"君津市","town_kanji":"","pref_code":"12","pref_roman":"Chiba-Ken","city_roman":"Kimitsu-Shi","town_roman":"Ikanikeisaiganaibaai"},"2991112":{"code":"12225","old_zip_code":"29911","zip_code":"2991112","pref_kana":"ﾁﾊﾞｹﾝ","city_kana":"ｷﾐﾂｼ","town_kana":"ｲｽﾞﾐ","pref_kanji":"千葉県","city_kanji":"君津市","town_kanji":"泉","pref_code":"12","pref_roman":"Chiba-Ken","city_roman":"Kimitsu-Shi","town_roman":"Izumi"},"2991175":{"code":"12225","old_zip_code":"29911","zip_code":"2991175","pref_kana":"ﾁﾊﾞｹﾝ","city_kana":"ｷﾐﾂｼ","town_kana":"ｳﾁﾐﾉﾜ","pref_kanji":"千葉県","city_kanji":"君津市","town_kanji":"内箕輪","pref_code":"12","pref_roman":"Chiba-Ken","city_roman":"Kimitsu-Shi","town_roman":"Uchiminowa"},"2991176":{"code":"12225","old_zip_code":"29911","zip_code":"2991176","pref_kana":"ﾁﾊﾞｹﾝ","city_kana":"ｷﾐﾂｼ","town_kana":"ｳﾁﾐﾉﾜ","pref_kanji":"千葉県","city_kanji":"君津市","town_kanji":"内蓑輪","pref_code":"12","pref_roman":"Chiba-Ken","city_roman":"Kimitsu-Shi","town_roman":"Uchiminowa"},"2991103":{"code":"12225","old_zip_code":"29911","zip_code":"2991103","pref_kana":"ﾁﾊﾞｹﾝ","city_kana":"ｷﾐﾂｼ","town_kana":"ｵｵｲ","pref_kanji":"千葉県","city_kanji":"君津市","town_kanji":"大井","pref_code":"12","pref_roman":"Chiba-Ken","city_roman":"Kimitsu-Shi","town_roman":"Oi"},"2991123":{"code":"12225","old_zip_code":"29911","zip_code":"2991123","pref_kana":"ﾁﾊﾞｹﾝ","city_kana":"ｷﾐﾂｼ","town_kana":"ｵｵﾔﾏﾉ","pref_kanji":"千葉県","city_kanji":"君津市","town_kanji":"大山野","pref_code":"12","pref_roman":"Chiba-Ken","city_roman":"Kimitsu-Shi","town_roman":"Oyamano"},"2991102":{"code":"12225","old_zip_code":"29911","zip_code":"2991102","pref_kana":"ﾁﾊﾞｹﾝ","city_kana":"ｷﾐﾂｼ","town_kana":"ｵｵﾜｼ","pref_kanji":"千葉県","city_kanji":"君津市","town_kanji":"大鷲","pref_code":"12","pref_roman":"Chiba-Ken","city_roman":"Kimitsu-Shi","town_roman":"Owashi"},"2991101":{"code":"12225","old_zip_code":"29911","zip_code":"2991101","pref_kana":"ﾁﾊﾞｹﾝ","city_kana":"ｷﾐﾂｼ","town_kana":"ｵｵﾜｼｼﾝﾃﾞﾝ","pref_kanji":"千葉県","city_kanji":"君津市","town_kanji":"大鷲新田","pref_code":"12","pref_roman":"Chiba-Ken","city_roman":"Kimitsu-Shi","town_roman":"Owashishinden"},"2991146":{"code":"12225","old_zip_code":"29911","zip_code":"2991146","pref_kana":"ﾁﾊﾞｹﾝ","city_kana":"ｷﾐﾂｼ","town_kana":"ｵｵﾜﾀﾞ","pref_kanji":"千葉県","city_kanji":"君津市","town_kanji":"大和田","pref_code":"12","pref_roman":"Chiba-Ken","city_roman":"Kimitsu-Shi","town_roman":"Owada"},"2991107":{"code":"12225","old_zip_code":"29911","zip_code":"2991107","pref_kana":"ﾁﾊﾞｹﾝ","city_kana":"ｷﾐﾂｼ","town_kana":"ｶﾐ","pref_kanji":"千葉県","city_kanji":"君津市","town_kanji":"上","pref_code":"12","pref_roman":"Chiba-Ken","city_roman":"Kimitsu-Shi","town_roman":"Kami"},"2991138":{"code":"12225","old_zip_code":"29911","zip_code":"2991138","pref_kana":"ﾁﾊﾞｹﾝ","city_kana":"ｷﾐﾂｼ","town_kana":"ｶﾐﾕｴ","pref_kanji":"千葉県","city_kanji":"君津市","town_kanji":"上湯江","pref_code":"12","pref_roman":"Chiba-Ken","city_roman":"Kimitsu-Shi","town_roman":"Kamiyue"},"2991164":{"code":"12225","old_zip_code":"29911","zip_code":"2991164","pref_kana":"ﾁﾊﾞｹﾝ","city_kana":"ｷﾐﾂｼ","town_kana":"ｷﾀｸﾎﾞ","pref_kanji":"千葉県","city_kanji":"君津市","town_kanji":"北久保","pref_code":"12","pref_roman":"Chiba-Ken","city_roman":"Kimitsu-Shi","town_roman":"Kitakubo"},"2991161":{"code":"12225","old_zip_code":"29911","zip_code":"2991161","pref_kana":"ﾁﾊﾞｹﾝ","city_kana":"ｷﾐﾂｼ","town_kana":"ｷﾀｺﾔｽ","pref_kanji":"千葉県","city_kanji":"君津市","town_kanji":"北子安","pref_code":"12","pref_roman":"Chiba-Ken","city_roman":"Kimitsu-Shi","town_roman":"Kitakoyasu"},"2991141":{"code":"12225","old_zip_code":"29911","zip_code":"2991141","pref_kana":"ﾁﾊﾞｹﾝ","city_kana":"ｷﾐﾂｼ","town_kana":"ｷﾐﾂ","pref_kanji":"千葉県","city_kanji":"君津市","town_kanji":"君津","pref_code":"12","pref_roman":"Chiba-Ken","city_roman":"Kimitsu-Shi","town_roman":"Kimitsu"},"2991143":{"code":"12225","old_zip_code":"29911","zip_code":"2991143","pref_kana":"ﾁﾊﾞｹﾝ","city_kana":"ｷﾐﾂｼ","town_kana":"ｷﾐﾂﾀﾞｲ","pref_kanji":"千葉県","city_kanji":"君津市","town_kanji":"君津台","pref_code":"12","pref_roman":"Chiba-Ken","city_roman":"Kimitsu-Shi","town_roman":"Kimitsudai"},"2991152":{"code":"12225","old_zip_code":"29911","zip_code":"2991152","pref_kana":"ﾁﾊﾞｹﾝ","city_kana":"ｷﾐﾂｼ","town_kana":"ｸﾎﾞ","pref_kanji":"千葉県","city_kanji":"君津市","town_kanji":"久保","pref_code":"12","pref_roman":"Chiba-Ken","city_roman":"Kimitsu-Shi","town_roman":"Kubo"},"2991165":{"code":"12225","old_zip_code":"29911","zip_code":"2991165","pref_kana":"ﾁﾊﾞｹﾝ","city_kana":"ｷﾐﾂｼ","town_kana":"ｺｳｻｶ","pref_kanji":"千葉県","city_kanji":"君津市","town_kanji":"高坂","pref_code":"12","pref_roman":"Chiba-Ken","city_roman":"Kimitsu-Shi","town_roman":"Kosaka"},"2991127":{"code":"12225","old_zip_code":"29911","zip_code":"2991127","pref_kana":"ﾁﾊﾞｹﾝ","city_kana":"ｷﾐﾂｼ","town_kana":"ｺｵﾘ","pref_kanji":"千葉県","city_kanji":"君津市","town_kanji":"郡","pref_code":"12","pref_roman":"Chiba-Ken","city_roman":"Kimitsu-Shi","town_roman":"Kori"},"2991126":{"code":"12225","old_zip_code":"29911","zip_code":"2991126","pref_kana":"ﾁﾊﾞｹﾝ","city_kana":"ｷﾐﾂｼ","town_kana":"ｺﾔﾏﾉ","pref_kanji":"千葉県","city_kanji":"君津市","town_kanji":"小山野","pref_code":"12","pref_roman":"Chiba-Ken","city_roman":"Kimitsu-Shi","town_roman":"Koyamano"},"2991142":{"code":"12225","old_zip_code":"29911","zip_code":"2991142","pref_kana":"ﾁﾊﾞｹﾝ","city_kana":"ｷﾐﾂｼ","town_kana":"ｻｶﾀﾞ","pref_kanji":"千葉県","city_kanji":"君津市","town_kanji":"坂田","pref_code":"12","pref_roman":"Chiba-Ken","city_roman":"Kimitsu-Shi","town_roman":"Sakada"},"2991133":{"code":"12225","old_zip_code":"29911","zip_code":"2991133","pref_kana":"ﾁﾊﾞｹﾝ","city_kana":"ｷﾐﾂｼ","town_kana":"ｻﾀﾞﾓﾄ","pref_kanji":"千葉県","city_kanji":"君津市","town_kanji":"貞元","pref_code":"12","pref_roman":"Chiba-Ken","city_roman":"Kimitsu-Shi","town_roman":"Sadamoto"},"2991116":{"code":"12225","old_zip_code":"29911","zip_code":"2991116","pref_kana":"ﾁﾊﾞｹﾝ","city_kana":"ｷﾐﾂｼ","town_kana":"ｻﾗﾋｷ","pref_kanji":"千葉県","city_kanji":"君津市","town_kanji":"皿引","pref_code":"12","pref_roman":"Chiba-Ken","city_roman":"Kimitsu-Shi","town_roman":"Sarahiki"},"2991136":{"code":"12225","old_zip_code":"29911","zip_code":"2991136","pref_kana":"ﾁﾊﾞｹﾝ","city_kana":"ｷﾐﾂｼ","town_kana":"ｼﾐﾄﾞｳ","pref_kanji":"千葉県","city_kanji":"君津市","town_kanji":"新御堂","pref_code":"12","pref_roman":"Chiba-Ken","city_roman":"Kimitsu-Shi","town_roman":"Shimido"},"2991131":{"code":"12225","old_zip_code":"29911","zip_code":"2991131","pref_kana":"ﾁﾊﾞｹﾝ","city_kana":"ｷﾐﾂｼ","town_kana":"ｼﾓﾕｴ","pref_kanji":"千葉県","city_kanji":"君津市","town_kanji":"下湯江","pref_code":"12","pref_roman":"Chiba-Ken","city_roman":"Kimitsu-Shi","town_roman":"Shimoyue"},"2991137":{"code":"12225","old_zip_code":"29911","zip_code":"2991137","pref_kana":"ﾁﾊﾞｹﾝ","city_kana":"ｷﾐﾂｼ","town_kana":"ｼｮｳｺｳ","pref_kanji":"千葉県","city_kanji":"君津市","town_kanji":"小香","pref_code":"12","pref_roman":"Chiba-Ken","city_roman":"Kimitsu-Shi","town_roman":"Shoko"},"2991105":{"code":"12225","old_zip_code":"29911","zip_code":"2991105","pref_kana":"ﾁﾊﾞｹﾝ","city_kana":"ｷﾐﾂｼ","town_kana":"ｼﾛｺﾏ","pref_kanji":"千葉県","city_kanji":"君津市","town_kanji":"白駒","pref_code":"12","pref_roman":"Chiba-Ken","city_roman":"Kimitsu-Shi","town_roman":"Shirokoma"},"2991135":{"code":"12225","old_zip_code":"29911","zip_code":"2991135","pref_kana":"ﾁﾊﾞｹﾝ","city_kana":"ｷﾐﾂｼ","town_kana":"ｽｷﾞﾔﾂ","pref_kanji":"千葉県","city_kanji":"君津市","town_kanji":"杉谷","pref_code":"12","pref_roman":"Chiba-Ken","city_roman":"Kimitsu-Shi","town_roman":"Sugiyatsu"},"2991114":{"code":"12225","old_zip_code":"29911","zip_code":"2991114","pref_kana":"ﾁﾊﾞｹﾝ","city_kana":"ｷﾐﾂｼ","town_kana":"ｿｳｷﾞｭｳ","pref_kanji":"千葉県","city_kanji":"君津市","town_kanji":"草牛","pref_code":"12","pref_roman":"Chiba-Ken","city_roman":"Kimitsu-Shi","town_roman":"Sogyu"},"2991173":{"code":"12225","old_zip_code":"29911","zip_code":"2991173","pref_kana":"ﾁﾊﾞｹﾝ","city_kana":"ｷﾐﾂｼ","town_kana":"ｿﾄﾐﾉﾜ","pref_kanji":"千葉県","city_kanji":"君津市","town_kanji":"外箕輪","pref_code":"12","pref_roman":"Chiba-Ken","city_roman":"Kimitsu-Shi","town_roman":"Sotominowa"},"2991153":{"code":"12225","old_zip_code":"29911","zip_code":"2991153","pref_kana":"ﾁﾊﾞｹﾝ","city_kana":"ｷﾐﾂｼ","town_kana":"ﾀﾞｲ","pref_kanji":"千葉県","city_kanji":"君津市","town_kanji":"台","pref_code":"12","pref_roman":"Chiba-Ken","city_roman":"Kimitsu-Shi","town_roman":"Dai"},"2991124":{"code":"12225","old_zip_code":"29911","zip_code":"2991124","pref_kana":"ﾁﾊﾞｹﾝ","city_kana":"ｷﾐﾂｼ","town_kana":"ﾂｸﾘｷ","pref_kanji":"千葉県","city_kanji":"君津市","town_kanji":"作木","pref_code":"12","pref_roman":"Chiba-Ken","city_roman":"Kimitsu-Shi","town_roman":"Tsukuriki"},"2991121":{"code":"12225","old_zip_code":"29911","zip_code":"2991121","pref_kana":"ﾁﾊﾞｹﾝ","city_kana":"ｷﾐﾂｼ","town_kana":"ﾄｺｼﾛ","pref_kanji":"千葉県","city_kanji":"君津市","town_kanji":"常代","pref_code":"12","pref_roman":"Chiba-Ken","city_roman":"Kimitsu-Shi","town_roman":"Tokoshiro"},"2991106":{"code":"12225","old_zip_code":"29911","zip_code":"2991106","pref_kana":"ﾁﾊﾞｹﾝ","city_kana":"ｷﾐﾂｼ","town_kana":"ﾅｶｼﾞﾏ","pref_kanji":"千葉県","city_kanji":"君津市","town_kanji":"中島","pref_code":"12","pref_roman":"Chiba-Ken","city_roman":"Kimitsu-Shi","town_roman":"Nakajima"},"2991132":{"code":"12225","old_zip_code":"29911","zip_code":"2991132","pref_kana":"ﾁﾊﾞｹﾝ","city_kana":"ｷﾐﾂｼ","town_kana":"ﾅｶﾄﾐ","pref_kanji":"千葉県","city_kanji":"君津市","town_kanji":"中富","pref_code":"12","pref_roman":"Chiba-Ken","city_roman":"Kimitsu-Shi","town_roman":"Nakatomi"},"2991151":{"code":"12225","old_zip_code":"29911","zip_code":"2991151","pref_kana":"ﾁﾊﾞｹﾝ","city_kana":"ｷﾐﾂｼ","town_kana":"ﾅｶﾉ","pref_kanji":"千葉県","city_kanji":"君津市","town_kanji":"中野","pref_code":"12","pref_roman":"Chiba-Ken","city_roman":"Kimitsu-Shi","town_roman":"Nakano"},"2991145":{"code":"12225","old_zip_code":"29911","zip_code":"2991145","pref_kana":"ﾁﾊﾞｹﾝ","city_kana":"ｷﾐﾂｼ","town_kana":"ﾆｼｻｶﾀﾞ","pref_kanji":"千葉県","city_kanji":"君津市","town_kanji":"西坂田","pref_code":"12","pref_roman":"Chiba-Ken","city_roman":"Kimitsu-Shi","town_roman":"Nishisakada"},"2991104":{"code":"12225","old_zip_code":"29911","zip_code":"2991104","pref_kana":"ﾁﾊﾞｹﾝ","city_kana":"ｷﾐﾂｼ","town_kana":"ﾇｶﾀ","pref_kanji":"千葉県","city_kanji":"君津市","town_kanji":"糠田","pref_code":"12","pref_roman":"Chiba-Ken","city_roman":"Kimitsu-Shi","town_roman":"Nukata"},"2991108":{"code":"12225","old_zip_code":"29911","zip_code":"2991108","pref_kana":"ﾁﾊﾞｹﾝ","city_kana":"ｷﾐﾂｼ","town_kana":"ﾈﾘｷ","pref_kanji":"千葉県","city_kanji":"君津市","town_kanji":"練木","pref_code":"12","pref_roman":"Chiba-Ken","city_roman":"Kimitsu-Shi","town_roman":"Neriki"},"2991122":{"code":"12225","old_zip_code":"29911","zip_code":"2991122","pref_kana":"ﾁﾊﾞｹﾝ","city_kana":"ｷﾐﾂｼ","town_kana":"ﾊﾏｺﾞ","pref_kanji":"千葉県","city_kanji":"君津市","town_kanji":"浜子","pref_code":"12","pref_roman":"Chiba-Ken","city_roman":"Kimitsu-Shi","town_roman":"Hamago"},"2991144":{"code":"12225","old_zip_code":"29911","zip_code":"2991144","pref_kana":"ﾁﾊﾞｹﾝ","city_kana":"ｷﾐﾂｼ","town_kana":"ﾋｶﾞｼｻｶﾀﾞ","pref_kanji":"千葉県","city_kanji":"君津市","town_kanji":"東坂田","pref_code":"12","pref_roman":"Chiba-Ken","city_roman":"Kimitsu-Shi","town_roman":"Higashisakada"},"2991113":{"code":"12225","old_zip_code":"29911","zip_code":"2991113","pref_kana":"ﾁﾊﾞｹﾝ","city_kana":"ｷﾐﾂｼ","town_kana":"ﾋﾞｼｬ","pref_kanji":"千葉県","city_kanji":"君津市","town_kanji":"尾車","pref_code":"12","pref_roman":"Chiba-Ken","city_roman":"Kimitsu-Shi","town_roman":"Bisha"},"2991147":{"code":"12225","old_zip_code":"29911","zip_code":"2991147","pref_kana":"ﾁﾊﾞｹﾝ","city_kana":"ｷﾐﾂｼ","town_kana":"ﾋﾄﾐ","pref_kanji":"千葉県","city_kanji":"君津市","town_kanji":"人見","pref_code":"12","pref_roman":"Chiba-Ken","city_roman":"Kimitsu-Shi","town_roman":"Hitomi"},"2991174":{"code":"12225","old_zip_code":"29911","zip_code":"2991174","pref_kana":"ﾁﾊﾞｹﾝ","city_kana":"ｷﾐﾂｼ","town_kana":"ﾎｳｷﾞｻｸ","pref_kanji":"千葉県","city_kanji":"君津市","town_kanji":"法木作","pref_code":"12","pref_roman":"Chiba-Ken","city_roman":"Kimitsu-Shi","town_roman":"Hogisaku"},"2991115":{"code":"12225","old_zip_code":"29911","zip_code":"2991115","pref_kana":"ﾁﾊﾞｹﾝ","city_kana":"ｷﾐﾂｼ","town_kana":"ﾏﾉﾎﾞﾘ","pref_kanji":"千葉県","city_kanji":"君津市","town_kanji":"馬登","pref_code":"12","pref_roman":"Chiba-Ken","city_roman":"Kimitsu-Shi","town_roman":"Manobori"},"2991154":{"code":"12225","old_zip_code":"29911","zip_code":"2991154","pref_kana":"ﾁﾊﾞｹﾝ","city_kana":"ｷﾐﾂｼ","town_kana":"ﾐﾅﾐｸﾎﾞ","pref_kanji":"千葉県","city_kanji":"君津市","town_kanji":"南久保","pref_code":"12","pref_roman":"Chiba-Ken","city_roman":"Kimitsu-Shi","town_roman":"Minamikubo"},"2991162":{"code":"12225","old_zip_code":"29911","zip_code":"2991162","pref_kana":"ﾁﾊﾞｹﾝ","city_kana":"ｷﾐﾂｼ","town_kana":"ﾐﾅﾐｺﾔｽ","pref_kanji":"千葉県","city_kanji":"君津市","town_kanji":"南子安","pref_code":"12","pref_roman":"Chiba-Ken","city_roman":"Kimitsu-Shi","town_roman":"Minamikoyasu"},"2991172":{"code":"12225","old_zip_code":"29911","zip_code":"2991172","pref_kana":"ﾁﾊﾞｹﾝ","city_kana":"ｷﾐﾂｼ","town_kana":"ﾐﾉｳ","pref_kanji":"千葉県","city_kanji":"君津市","town_kanji":"三直","pref_code":"12","pref_roman":"Chiba-Ken","city_roman":"Kimitsu-Shi","town_roman":"Mino"},"2991117":{"code":"12225","old_zip_code":"29911","zip_code":"2991117","pref_kana":"ﾁﾊﾞｹﾝ","city_kana":"ｷﾐﾂｼ","town_kana":"ﾐﾔﾉｼﾀ","pref_kanji":"千葉県","city_kanji":"君津市","town_kanji":"宮下","pref_code":"12","pref_roman":"Chiba-Ken","city_roman":"Kimitsu-Shi","town_roman":"Miyanoshita"},"2991111":{"code":"12225","old_zip_code":"29911","zip_code":"2991111","pref_kana":"ﾁﾊﾞｹﾝ","city_kana":"ｷﾐﾂｼ","town_kana":"ﾑﾃ","pref_kanji":"千葉県","city_kanji":"君津市","town_kanji":"六手","pref_code":"12","pref_roman":"Chiba-Ken","city_roman":"Kimitsu-Shi","town_roman":"Mute"},"2991163":{"code":"12225","old_zip_code":"29911","zip_code":"2991163","pref_kana":"ﾁﾊﾞｹﾝ","city_kana":"ｷﾐﾂｼ","town_kana":"ﾓｸｼ","pref_kanji":"千葉県","city_kanji":"君津市","town_kanji":"杢師","pref_code":"12","pref_roman":"Chiba-Ken","city_roman":"Kimitsu-Shi","town_roman":"Mokushi"},"2991171":{"code":"12225","old_zip_code":"29911","zip_code":"2991171","pref_kana":"ﾁﾊﾞｹﾝ","city_kana":"ｷﾐﾂｼ","town_kana":"ﾔｴﾊﾗ","pref_kanji":"千葉県","city_kanji":"君津市","town_kanji":"八重原","pref_code":"12","pref_roman":"Chiba-Ken","city_roman":"Kimitsu-Shi","town_roman":"Yaehara"},"2991125":{"code":"12225","old_zip_code":"29911","zip_code":"2991125","pref_kana":"ﾁﾊﾞｹﾝ","city_kana":"ｷﾐﾂｼ","town_kana":"ﾔﾏﾀｶﾊﾗ","pref_kanji":"千葉県","city_kanji":"君津市","town_kanji":"山高原","pref_code":"12","pref_roman":"Chiba-Ken","city_roman":"Kimitsu-Shi","town_roman":"Yamatakahara"},"2991134":{"code":"12225","old_zip_code":"29911","zip_code":"2991134","pref_kana":"ﾁﾊﾞｹﾝ","city_kana":"ｷﾐﾂｼ","town_kana":"ﾔﾜﾀ","pref_kanji":"千葉県","city_kanji":"君津市","town_kanji":"八幡","pref_code":"12","pref_roman":"Chiba-Ken","city_roman":"Kimitsu-Shi","town_roman":"Yawata"},"2991166":{"code":"12225","old_zip_code":"29911","zip_code":"2991166","pref_kana":"ﾁﾊﾞｹﾝ","city_kana":"ｷﾐﾂｼ","town_kana":"ﾖｳｺｳﾀﾞｲ","pref_kanji":"千葉県","city_kanji":"君津市","town_kanji":"陽光台","pref_code":"12","pref_roman":"Chiba-Ken","city_roman":"Kimitsu-Shi","town_roman":"Yokodai"},"2991615":{"code":"12226","old_zip_code":"29916","zip_code":"2991615","pref_kana":"ﾁﾊﾞｹﾝ","city_kana":"ﾌｯﾂｼ","town_kana":"ｱｲｶﾜ","pref_kanji":"千葉県","city_kanji":"富津市","town_kanji":"相川","pref_code":"12","pref_roman":"Chiba-Ken","city_roman":"Futtsu-Shi","town_roman":"Aikawa"},"2991613":{"code":"12226","old_zip_code":"29916","zip_code":"2991613","pref_kana":"ﾁﾊﾞｹﾝ","city_kana":"ﾌｯﾂｼ","town_kana":"ｲﾘﾔﾏｽﾞ","pref_kanji":"千葉県","city_kanji":"富津市","town_kanji":"不入斗","pref_code":"12","pref_roman":"Chiba-Ken","city_roman":"Futtsu-Shi","town_roman":"Iriyamazu"},"2991608":{"code":"12226","old_zip_code":"29916","zip_code":"2991608","pref_kana":"ﾁﾊﾞｹﾝ","city_kana":"ﾌｯﾂｼ","town_kana":"ｲﾜｻｶ","pref_kanji":"千葉県","city_kanji":"富津市","town_kanji":"岩坂","pref_code":"12","pref_roman":"Chiba-Ken","city_roman":"Futtsu-Shi","town_roman":"Iwasaka"},"2991746":{"code":"12226","old_zip_code":"29917","zip_code":"2991746","pref_kana":"ﾁﾊﾞｹﾝ","city_kana":"ﾌｯﾂｼ","town_kana":"ｲﾜﾓﾄ","pref_kanji":"千葉県","city_kanji":"富津市","town_kanji":"岩本","pref_code":"12","pref_roman":"Chiba-Ken","city_roman":"Futtsu-Shi","town_roman":"Iwamoto"},"2991753":{"code":"12226","old_zip_code":"29917","zip_code":"2991753","pref_kana":"ﾁﾊﾞｹﾝ","city_kana":"ﾌｯﾂｼ","town_kana":"ｳｴｺﾞ","pref_kanji":"千葉県","city_kanji":"富津市","town_kanji":"上後","pref_code":"12","pref_roman":"Chiba-Ken","city_roman":"Futtsu-Shi","town_roman":"Uego"},"2991732":{"code":"12226","old_zip_code":"29917","zip_code":"2991732","pref_kana":"ﾁﾊﾞｹﾝ","city_kana":"ﾌｯﾂｼ","town_kana":"ｳﾄｳﾊﾞﾗ","pref_kanji":"千葉県","city_kanji":"富津市","town_kanji":"宇藤原","pref_code":"12","pref_roman":"Chiba-Ken","city_roman":"Futtsu-Shi","town_roman":"Utobara"},"2991617":{"code":"12226","old_zip_code":"29916","zip_code":"2991617","pref_kana":"ﾁﾊﾞｹﾝ","city_kana":"ﾌｯﾂｼ","town_kana":"ｳﾙﾂﾞ","pref_kanji":"千葉県","city_kanji":"富津市","town_kanji":"売津","pref_code":"12","pref_roman":"Chiba-Ken","city_roman":"Futtsu-Shi","town_roman":"Uruzu"},"2991736":{"code":"12226","old_zip_code":"29917","zip_code":"2991736","pref_kana":"ﾁﾊﾞｹﾝ","city_kana":"ﾌｯﾂｼ","town_kana":"ｵｵｶﾞﾜｻｷ","pref_kanji":"千葉県","city_kanji":"富津市","town_kanji":"大川崎","pref_code":"12","pref_roman":"Chiba-Ken","city_roman":"Futtsu-Shi","town_roman":"Ogawasaki"},"2991735":{"code":"12226","old_zip_code":"29917","zip_code":"2991735","pref_kana":"ﾁﾊﾞｹﾝ","city_kana":"ﾌｯﾂｼ","town_kana":"ｵｵﾀﾜ","pref_kanji":"千葉県","city_kanji":"富津市","town_kanji":"大田和","pref_code":"12","pref_roman":"Chiba-Ken","city_roman":"Futtsu-Shi","town_roman":"Otawa"},"2991758":{"code":"12226","old_zip_code":"29917","zip_code":"2991758","pref_kana":"ﾁﾊﾞｹﾝ","city_kana":"ﾌｯﾂｼ","town_kana":"ｵｵﾓﾘ","pref_kanji":"千葉県","city_kanji":"富津市","town_kanji":"大森","pref_code":"12","pref_roman":"Chiba-Ken","city_roman":"Futtsu-Shi","town_roman":"Omori"},"2991757":{"code":"12226","old_zip_code":"29917","zip_code":"2991757","pref_kana":"ﾁﾊﾞｹﾝ","city_kana":"ﾌｯﾂｼ","town_kana":"ｵｼｷﾘ","pref_kanji":"千葉県","city_kanji":"富津市","town_kanji":"押切","pref_code":"12","pref_roman":"Chiba-Ken","city_roman":"Futtsu-Shi","town_roman":"Oshikiri"},"2991751":{"code":"12226","old_zip_code":"29917","zip_code":"2991751","pref_kana":"ﾁﾊﾞｹﾝ","city_kana":"ﾌｯﾂｼ","town_kana":"ｵﾝﾀﾞ","pref_kanji":"千葉県","city_kanji":"富津市","town_kanji":"恩田","pref_code":"12","pref_roman":"Chiba-Ken","city_roman":"Futtsu-Shi","town_roman":"Onda"},"2991616":{"code":"12226","old_zip_code":"29916","zip_code":"2991616","pref_kana":"ﾁﾊﾞｹﾝ","city_kana":"ﾌｯﾂｼ","town_kana":"ｶｲﾗ","pref_kanji":"千葉県","city_kanji":"富津市","town_kanji":"海良","pref_code":"12","pref_roman":"Chiba-Ken","city_roman":"Futtsu-Shi","town_roman":"Kaira"},"2991606":{"code":"12226","old_zip_code":"29916","zip_code":"2991606","pref_kana":"ﾁﾊﾞｹﾝ","city_kana":"ﾌｯﾂｼ","town_kana":"ｶｽﾞﾏ","pref_kanji":"千葉県","city_kanji":"富津市","town_kanji":"数馬","pref_code":"12","pref_roman":"Chiba-Ken","city_roman":"Futtsu-Shi","town_roman":"Kazuma"},"2991609":{"code":"12226","old_zip_code":"29916","zip_code":"2991609","pref_kana":"ﾁﾊﾞｹﾝ","city_kana":"ﾌｯﾂｼ","town_kana":"ｶﾄｳ","pref_kanji":"千葉県","city_kanji":"富津市","town_kanji":"加藤","pref_code":"12","pref_roman":"Chiba-Ken","city_roman":"Futtsu-Shi","town_roman":"Kato"},"2991861":{"code":"12226","old_zip_code":"29918","zip_code":"2991861","pref_kana":"ﾁﾊﾞｹﾝ","city_kana":"ﾌｯﾂｼ","town_kana":"ｶﾅﾔ","pref_kanji":"千葉県","city_kanji":"富津市","town_kanji":"金谷","pref_code":"12","pref_roman":"Chiba-Ken","city_roman":"Futtsu-Shi","town_roman":"Kanaya"},"2991747":{"code":"12226","old_zip_code":"29917","zip_code":"2991747","pref_kana":"ﾁﾊﾞｹﾝ","city_kana":"ﾌｯﾂｼ","town_kana":"ｺｼﾞｺﾏ","pref_kanji":"千葉県","city_kanji":"富津市","town_kanji":"小志駒","pref_code":"12","pref_roman":"Chiba-Ken","city_roman":"Futtsu-Shi","town_roman":"Kojikoma"},"2991602":{"code":"12226","old_zip_code":"29916","zip_code":"2991602","pref_kana":"ﾁﾊﾞｹﾝ","city_kana":"ﾌｯﾂｼ","town_kana":"ｻｸﾗｲ","pref_kanji":"千葉県","city_kanji":"富津市","town_kanji":"桜井","pref_code":"12","pref_roman":"Chiba-Ken","city_roman":"Futtsu-Shi","town_roman":"Sakurai"},"2991601":{"code":"12226","old_zip_code":"29916","zip_code":"2991601","pref_kana":"ﾁﾊﾞｹﾝ","city_kana":"ﾌｯﾂｼ","town_kana":"ｻｸﾗｲｿｳｼｮｳｷﾅﾀﾞﾔﾏ","pref_kanji":"千葉県","city_kanji":"富津市","town_kanji":"桜井総稱鬼泪山","pref_code":"12","pref_roman":"Chiba-Ken","city_roman":"Futtsu-Shi","town_roman":"Sakuraisoshokinadayama"},"2991603":{"code":"12226","old_zip_code":"29916","zip_code":"2991603","pref_kana":"ﾁﾊﾞｹﾝ","city_kana":"ﾌｯﾂｼ","town_kana":"ｻﾗﾜ","pref_kanji":"千葉県","city_kanji":"富津市","town_kanji":"更和","pref_code":"12","pref_roman":"Chiba-Ken","city_roman":"Futtsu-Shi","town_roman":"Sarawa"},"2991745":{"code":"12226","old_zip_code":"29917","zip_code":"2991745","pref_kana":"ﾁﾊﾞｹﾝ","city_kana":"ﾌｯﾂｼ","town_kana":"ｼｺﾏ","pref_kanji":"千葉県","city_kanji":"富津市","town_kanji":"志駒","pref_code":"12","pref_roman":"Chiba-Ken","city_roman":"Futtsu-Shi","town_roman":"Shikoma"},"2991734":{"code":"12226","old_zip_code":"29917","zip_code":"2991734","pref_kana":"ﾁﾊﾞｹﾝ","city_kana":"ﾌｯﾂｼ","town_kana":"ｾｷ","pref_kanji":"千葉県","city_kanji":"富津市","town_kanji":"関","pref_code":"12","pref_roman":"Chiba-Ken","city_roman":"Futtsu-Shi","town_roman":"Seki"},"2991752":{"code":"12226","old_zip_code":"29917","zip_code":"2991752","pref_kana":"ﾁﾊﾞｹﾝ","city_kana":"ﾌｯﾂｼ","town_kana":"ｾｷｼﾞﾘ","pref_kanji":"千葉県","city_kanji":"富津市","town_kanji":"関尻","pref_code":"12","pref_roman":"Chiba-Ken","city_roman":"Futtsu-Shi","town_roman":"Sekijiri"},"2991604":{"code":"12226","old_zip_code":"29916","zip_code":"2991604","pref_kana":"ﾁﾊﾞｹﾝ","city_kana":"ﾌｯﾂｼ","town_kana":"ﾀﾞｲﾊﾞﾗ","pref_kanji":"千葉県","city_kanji":"富津市","town_kanji":"台原","pref_code":"12","pref_roman":"Chiba-Ken","city_roman":"Futtsu-Shi","town_roman":"Daibara"},"2991733":{"code":"12226","old_zip_code":"29917","zip_code":"2991733","pref_kana":"ﾁﾊﾞｹﾝ","city_kana":"ﾌｯﾂｼ","town_kana":"ﾀｶﾐｿﾞ","pref_kanji":"千葉県","city_kanji":"富津市","town_kanji":"高溝","pref_code":"12","pref_roman":"Chiba-Ken","city_roman":"Futtsu-Shi","town_roman":"Takamizo"},"2991731":{"code":"12226","old_zip_code":"29917","zip_code":"2991731","pref_kana":"ﾁﾊﾞｹﾝ","city_kana":"ﾌｯﾂｼ","town_kana":"ﾀｸﾞﾗ","pref_kanji":"千葉県","city_kanji":"富津市","town_kanji":"田倉","pref_code":"12","pref_roman":"Chiba-Ken","city_roman":"Futtsu-Shi","town_roman":"Tagura"},"2991621":{"code":"12226","old_zip_code":"29916","zip_code":"2991621","pref_kana":"ﾁﾊﾞｹﾝ","city_kana":"ﾌｯﾂｼ","town_kana":"ﾀｹｵｶ","pref_kanji":"千葉県","city_kanji":"富津市","town_kanji":"竹岡","pref_code":"12","pref_roman":"Chiba-Ken","city_roman":"Futtsu-Shi","town_roman":"Takeoka"},"2991755":{"code":"12226","old_zip_code":"29917","zip_code":"2991755","pref_kana":"ﾁﾊﾞｹﾝ","city_kana":"ﾌｯﾂｼ","town_kana":"ﾀﾊﾞﾗ","pref_kanji":"千葉県","city_kanji":"富津市","town_kanji":"田原","pref_code":"12","pref_roman":"Chiba-Ken","city_roman":"Futtsu-Shi","town_roman":"Tabara"},"2991759":{"code":"12226","old_zip_code":"29917","zip_code":"2991759","pref_kana":"ﾁﾊﾞｹﾝ","city_kana":"ﾌｯﾂｼ","town_kana":"ﾃﾗｵ","pref_kanji":"千葉県","city_kanji":"富津市","town_kanji":"寺尾","pref_code":"12","pref_roman":"Chiba-Ken","city_roman":"Futtsu-Shi","town_roman":"Terao"},"2991742":{"code":"12226","old_zip_code":"29917","zip_code":"2991742","pref_kana":"ﾁﾊﾞｹﾝ","city_kana":"ﾌｯﾂｼ","town_kana":"ﾄﾖｵｶ","pref_kanji":"千葉県","city_kanji":"富津市","town_kanji":"豊岡","pref_code":"12","pref_roman":"Chiba-Ken","city_roman":"Futtsu-Shi","town_roman":"Toyoka"},"2991611":{"code":"12226","old_zip_code":"29916","zip_code":"2991611","pref_kana":"ﾁﾊﾞｹﾝ","city_kana":"ﾌｯﾂｼ","town_kana":"ﾅｶﾞｻｷ","pref_kanji":"千葉県","city_kanji":"富津市","town_kanji":"長崎","pref_code":"12","pref_roman":"Chiba-Ken","city_roman":"Futtsu-Shi","town_roman":"Nagasaki"},"2991744":{"code":"12226","old_zip_code":"29917","zip_code":"2991744","pref_kana":"ﾁﾊﾞｹﾝ","city_kana":"ﾌｯﾂｼ","town_kana":"ﾅｼｻﾞﾜ","pref_kanji":"千葉県","city_kanji":"富津市","town_kanji":"梨沢","pref_code":"12","pref_roman":"Chiba-Ken","city_roman":"Futtsu-Shi","town_roman":"Nashizawa"},"2991614":{"code":"12226","old_zip_code":"29916","zip_code":"2991614","pref_kana":"ﾁﾊﾞｹﾝ","city_kana":"ﾌｯﾂｼ","town_kana":"ﾅｼｻﾞﾜ","pref_kanji":"千葉県","city_kanji":"富津市","town_kanji":"梨沢","pref_code":"12","pref_roman":"Chiba-Ken","city_roman":"Futtsu-Shi","town_roman":"Nashizawa"},"2991622":{"code":"12226","old_zip_code":"29916","zip_code":"2991622","pref_kana":"ﾁﾊﾞｹﾝ","city_kana":"ﾌｯﾂｼ","town_kana":"ﾊｷﾞｳ","pref_kanji":"千葉県","city_kanji":"富津市","town_kanji":"萩生","pref_code":"12","pref_roman":"Chiba-Ken","city_roman":"Futtsu-Shi","town_roman":"Hagiu"},"2991618":{"code":"12226","old_zip_code":"29916","zip_code":"2991618","pref_kana":"ﾁﾊﾞｹﾝ","city_kana":"ﾌｯﾂｼ","town_kana":"ﾊﾅﾜ","pref_kanji":"千葉県","city_kanji":"富津市","town_kanji":"花輪","pref_code":"12","pref_roman":"Chiba-Ken","city_roman":"Futtsu-Shi","town_roman":"Hanawa"},"2991737":{"code":"12226","old_zip_code":"29917","zip_code":"2991737","pref_kana":"ﾁﾊﾞｹﾝ","city_kana":"ﾌｯﾂｼ","town_kana":"ﾋｶﾞｼｵｵﾜﾀﾞ","pref_kanji":"千葉県","city_kanji":"富津市","town_kanji":"東大和田","pref_code":"12","pref_roman":"Chiba-Ken","city_roman":"Futtsu-Shi","town_roman":"Higashiowada"},"2991607":{"code":"12226","old_zip_code":"29916","zip_code":"2991607","pref_kana":"ﾁﾊﾞｹﾝ","city_kana":"ﾌｯﾂｼ","town_kana":"ﾐﾅﾄ","pref_kanji":"千葉県","city_kanji":"富津市","town_kanji":"湊","pref_code":"12","pref_roman":"Chiba-Ken","city_roman":"Futtsu-Shi","town_roman":"Minato"},"2991741":{"code":"12226","old_zip_code":"29917","zip_code":"2991741","pref_kana":"ﾁﾊﾞｹﾝ","city_kana":"ﾌｯﾂｼ","town_kana":"ﾐﾖﾊﾞﾗ","pref_kanji":"千葉県","city_kanji":"富津市","town_kanji":"御代原","pref_code":"12","pref_roman":"Chiba-Ken","city_roman":"Futtsu-Shi","town_roman":"Miyobara"},"2991756":{"code":"12226","old_zip_code":"29917","zip_code":"2991756","pref_kana":"ﾁﾊﾞｹﾝ","city_kana":"ﾌｯﾂｼ","town_kana":"ﾑﾂﾉ","pref_kanji":"千葉県","city_kanji":"富津市","town_kanji":"六野","pref_code":"12","pref_roman":"Chiba-Ken","city_roman":"Futtsu-Shi","town_roman":"Mutsuno"},"2991605":{"code":"12226","old_zip_code":"29916","zip_code":"2991605","pref_kana":"ﾁﾊﾞｹﾝ","city_kana":"ﾌｯﾂｼ","town_kana":"ﾓﾁｲ","pref_kanji":"千葉県","city_kanji":"富津市","town_kanji":"望井","pref_code":"12","pref_roman":"Chiba-Ken","city_roman":"Futtsu-Shi","town_roman":"Mochii"},"2991743":{"code":"12226","old_zip_code":"29917","zip_code":"2991743","pref_kana":"ﾁﾊﾞｹﾝ","city_kana":"ﾌｯﾂｼ","town_kana":"ﾔﾏﾅｶ","pref_kanji":"千葉県","city_kanji":"富津市","town_kanji":"山中","pref_code":"12","pref_roman":"Chiba-Ken","city_roman":"Futtsu-Shi","town_roman":"Yamanaka"},"2991754":{"code":"12226","old_zip_code":"29917","zip_code":"2991754","pref_kana":"ﾁﾊﾞｹﾝ","city_kana":"ﾌｯﾂｼ","town_kana":"ﾔﾏﾜｷ","pref_kanji":"千葉県","city_kanji":"富津市","town_kanji":"山脇","pref_code":"12","pref_roman":"Chiba-Ken","city_roman":"Futtsu-Shi","town_roman":"Yamawaki"},"2991612":{"code":"12226","old_zip_code":"29916","zip_code":"2991612","pref_kana":"ﾁﾊﾞｹﾝ","city_kana":"ﾌｯﾂｼ","town_kana":"ﾖｺﾔﾏ","pref_kanji":"千葉県","city_kanji":"富津市","town_kanji":"横山","pref_code":"12","pref_roman":"Chiba-Ken","city_roman":"Futtsu-Shi","town_roman":"Yokoyama"},"2991905":{"code":"12463","old_zip_code":"29919","zip_code":"2991905","pref_kana":"ﾁﾊﾞｹﾝ","city_kana":"ｱﾜｸﾞﾝｷｮﾅﾝﾏﾁ","town_kana":"ｲﾁｲﾊﾞﾗ","pref_kanji":"千葉県","city_kanji":"安房郡鋸南町","town_kanji":"市井原","pref_code":"12","pref_roman":"Chiba-Ken","city_roman":"Awa-Gun Kyonan-Machi","town_roman":"Ichiibara"},"2991907":{"code":"12463","old_zip_code":"29919","zip_code":"2991907","pref_kana":"ﾁﾊﾞｹﾝ","city_kana":"ｱﾜｸﾞﾝｷｮﾅﾝﾏﾁ","town_kana":"ｴﾂﾞｷ","pref_kanji":"千葉県","city_kanji":"安房郡鋸南町","town_kanji":"江月","pref_code":"12","pref_roman":"Chiba-Ken","city_roman":"Awa-Gun Kyonan-Machi","town_roman":"Ezuki"},"2991903":{"code":"12463","old_zip_code":"29919","zip_code":"2991903","pref_kana":"ﾁﾊﾞｹﾝ","city_kana":"ｱﾜｸﾞﾝｷｮﾅﾝﾏﾁ","town_kana":"ｵｵｶﾀﾋﾞﾗ","pref_kanji":"千葉県","city_kanji":"安房郡鋸南町","town_kanji":"大帷子","pref_code":"12","pref_roman":"Chiba-Ken","city_roman":"Awa-Gun Kyonan-Machi","town_roman":"Okatabira"},"2991904":{"code":"12463","old_zip_code":"29919","zip_code":"2991904","pref_kana":"ﾁﾊﾞｹﾝ","city_kana":"ｱﾜｸﾞﾝｷｮﾅﾝﾏﾁ","town_kana":"ｺﾎﾞﾀ","pref_kanji":"千葉県","city_kanji":"安房郡鋸南町","town_kanji":"小保田","pref_code":"12","pref_roman":"Chiba-Ken","city_roman":"Awa-Gun Kyonan-Machi","town_roman":"Kobota"},"2991909":{"code":"12463","old_zip_code":"29919","zip_code":"2991909","pref_kana":"ﾁﾊﾞｹﾝ","city_kana":"ｱﾜｸﾞﾝｷｮﾅﾝﾏﾁ","town_kana":"ﾀﾞｲﾛｸ","pref_kanji":"千葉県","city_kanji":"安房郡鋸南町","town_kanji":"大六","pref_code":"12","pref_roman":"Chiba-Ken","city_roman":"Awa-Gun Kyonan-Machi","town_roman":"Dairoku"},"2991902":{"code":"12463","old_zip_code":"29919","zip_code":"2991902","pref_kana":"ﾁﾊﾞｹﾝ","city_kana":"ｱﾜｸﾞﾝｷｮﾅﾝﾏﾁ","town_kana":"ﾎﾀ","pref_kanji":"千葉県","city_kanji":"安房郡鋸南町","town_kanji":"保田","pref_code":"12","pref_roman":"Chiba-Ken","city_roman":"Awa-Gun Kyonan-Machi","town_roman":"Hota"},"2991901":{"code":"12463","old_zip_code":"29919","zip_code":"2991901","pref_kana":"ﾁﾊﾞｹﾝ","city_kana":"ｱﾜｸﾞﾝｷｮﾅﾝﾏﾁ","town_kana":"ﾓﾄﾅ","pref_kanji":"千葉県","city_kanji":"安房郡鋸南町","town_kanji":"元名","pref_code":"12","pref_roman":"Chiba-Ken","city_roman":"Awa-Gun Kyonan-Machi","town_roman":"Motona"},"2991906":{"code":"12463","old_zip_code":"29919","zip_code":"2991906","pref_kana":"ﾁﾊﾞｹﾝ","city_kana":"ｱﾜｸﾞﾝｷｮﾅﾝﾏﾁ","town_kana":"ﾖｺﾈ","pref_kanji":"千葉県","city_kanji":"安房郡鋸南町","town_kanji":"横根","pref_code":"12","pref_roman":"Chiba-Ken","city_roman":"Awa-Gun Kyonan-Machi","town_roman":"Yokone"},"2991908":{"code":"12463","old_zip_code":"29919","zip_code":"2991908","pref_kana":"ﾁﾊﾞｹﾝ","city_kana":"ｱﾜｸﾞﾝｷｮﾅﾝﾏﾁ","town_kana":"ﾖｼﾊﾏ","pref_kanji":"千葉県","city_kanji":"安房郡鋸南町","town_kanji":"吉浜","pref_code":"12","pref_roman":"Chiba-Ken","city_roman":"Awa-Gun Kyonan-Machi","town_roman":"Yoshihama"}}
