{"5152523":{"code":"24201","old_zip_code":"51525","zip_code":"5152523","pref_kana":"ﾐｴｹﾝ","city_kana":"ﾂｼ","town_kana":"ｲﾁｼﾁｮｳｲｳ","pref_kanji":"三重県","city_kanji":"津市","town_kanji":"一志町井生","pref_roman":"MIE KEN","city_roman":"TSU SHI","town_roman":"ICHISHICHO IU"},"5152525":{"code":"24201","old_zip_code":"51525","zip_code":"5152525","pref_kana":"ﾐｴｹﾝ","city_kana":"ﾂｼ","town_kana":"ｲﾁｼﾁｮｳｲｼﾊﾞｼ","pref_kanji":"三重県","city_kanji":"津市","town_kanji":"一志町石橋","pref_roman":"MIE KEN","city_roman":"TSU SHI","town_roman":"ICHISHICHO ISHIBASHI"},"5152521":{"code":"24201","old_zip_code":"51525","zip_code":"5152521","pref_kana":"ﾐｴｹﾝ","city_kana":"ﾂｼ","town_kana":"ｲﾁｼﾁｮｳｲｾｷﾞ","pref_kanji":"三重県","city_kanji":"津市","town_kanji":"一志町井関","pref_roman":"MIE KEN","city_roman":"TSU SHI","town_roman":"ICHISHICHO ISEGI"},"5152524":{"code":"24201","old_zip_code":"51525","zip_code":"5152524","pref_kana":"ﾐｴｹﾝ","city_kana":"ﾂｼ","town_kana":"ｲﾁｼﾁｮｳｵｵﾉｷ","pref_kanji":"三重県","city_kanji":"津市","town_kanji":"一志町大仰","pref_roman":"MIE KEN","city_roman":"TSU SHI","town_roman":"ICHISHICHO ONOKI"},"5152514":{"code":"24201","old_zip_code":"51525","zip_code":"5152514","pref_kana":"ﾐｴｹﾝ","city_kana":"ﾂｼ","town_kana":"ｲﾁｼﾁｮｳｵﾔﾏ(ｿﾉﾀ)","pref_kanji":"三重県","city_kanji":"津市","town_kanji":"一志町小山（その他）","pref_roman":"MIE KEN","city_roman":"TSU SHI","town_roman":"ICHISHICHO OYAMA(SONOTA)"},"5152511":{"code":"24201","old_zip_code":"51525","zip_code":"5152511","pref_kana":"ﾐｴｹﾝ","city_kana":"ﾂｼ","town_kana":"ｲﾁｼﾁｮｳｶﾀﾉ","pref_kanji":"三重県","city_kanji":"津市","town_kanji":"一志町片野","pref_roman":"MIE KEN","city_roman":"TSU SHI","town_roman":"ICHISHICHO KATANO"},"5152505":{"code":"24201","old_zip_code":"51525","zip_code":"5152505","pref_kana":"ﾐｴｹﾝ","city_kana":"ﾂｼ","town_kana":"ｲﾁｼﾁｮｳｺﾍﾞｷ","pref_kanji":"三重県","city_kanji":"津市","town_kanji":"一志町小戸木","pref_roman":"MIE KEN","city_roman":"TSU SHI","town_roman":"ICHISHICHO KOBEKI"},"5152501":{"code":"24201","old_zip_code":"51525","zip_code":"5152501","pref_kana":"ﾐｴｹﾝ","city_kana":"ﾂｼ","town_kana":"ｲﾁｼﾁｮｳｼｮｳﾑﾗ","pref_kanji":"三重県","city_kanji":"津市","town_kanji":"一志町庄村","pref_roman":"MIE KEN","city_roman":"TSU SHI","town_roman":"ICHISHICHO SHOMURA"},"5152512":{"code":"24201","old_zip_code":"51525","zip_code":"5152512","pref_kana":"ﾐｴｹﾝ","city_kana":"ﾂｼ","town_kana":"ｲﾁｼﾁｮｳｼﾝｻﾜﾀﾞ","pref_kanji":"三重県","city_kanji":"津市","town_kanji":"一志町新沢田","pref_roman":"MIE KEN","city_roman":"TSU SHI","town_roman":"ICHISHICHO SHINSAWADA"},"5152526":{"code":"24201","old_zip_code":"51525","zip_code":"5152526","pref_kana":"ﾐｴｹﾝ","city_kana":"ﾂｼ","town_kana":"ｲﾁｼﾁｮｳｿﾉｸﾗ","pref_kanji":"三重県","city_kanji":"津市","town_kanji":"一志町其倉","pref_roman":"MIE KEN","city_roman":"TSU SHI","town_roman":"ICHISHICHO SONOKURA"},"5152502":{"code":"24201","old_zip_code":"51525","zip_code":"5152502","pref_kana":"ﾐｴｹﾝ","city_kana":"ﾂｼ","town_kana":"ｲﾁｼﾁｮｳｿﾉﾑﾗ","pref_kanji":"三重県","city_kanji":"津市","town_kanji":"一志町其村","pref_roman":"MIE KEN","city_roman":"TSU SHI","town_roman":"ICHISHICHO SONOMURA"},"5152504":{"code":"24201","old_zip_code":"51525","zip_code":"5152504","pref_kana":"ﾐｴｹﾝ","city_kana":"ﾂｼ","town_kana":"ｲﾁｼﾁｮｳﾀｶﾉ(ｿﾉﾀ)","pref_kanji":"三重県","city_kanji":"津市","town_kanji":"一志町高野（その他）","pref_roman":"MIE KEN","city_roman":"TSU SHI","town_roman":"ICHISHICHO TAKANO(SONOTA)"},"5152516":{"code":"24201","old_zip_code":"51525","zip_code":"5152516","pref_kana":"ﾐｴｹﾝ","city_kana":"ﾂｼ","town_kana":"ｲﾁｼﾁｮｳﾀｼﾞﾘ","pref_kanji":"三重県","city_kanji":"津市","town_kanji":"一志町田尻","pref_roman":"MIE KEN","city_roman":"TSU SHI","town_roman":"ICHISHICHO TAJIRI"},"5152513":{"code":"24201","old_zip_code":"51525","zip_code":"5152513","pref_kana":"ﾐｴｹﾝ","city_kana":"ﾂｼ","town_kana":"ｲﾁｼﾁｮｳﾆｼﾞｶﾞｵｶ","pref_kanji":"三重県","city_kanji":"津市","town_kanji":"一志町虹が丘","pref_roman":"MIE KEN","city_roman":"TSU SHI","town_roman":"ICHISHICHO NIJIGAOKA"},"5152522":{"code":"24201","old_zip_code":"51525","zip_code":"5152522","pref_kana":"ﾐｴｹﾝ","city_kana":"ﾂｼ","town_kana":"ｲﾁｼﾁｮｳﾊｾﾞ","pref_kanji":"三重県","city_kanji":"津市","town_kanji":"一志町波瀬","pref_roman":"MIE KEN","city_roman":"TSU SHI","town_roman":"ICHISHICHO HAZE"},"5152515":{"code":"24201","old_zip_code":"51525","zip_code":"5152515","pref_kana":"ﾐｴｹﾝ","city_kana":"ﾂｼ","town_kana":"ｲﾁｼﾁｮｳﾊﾀ(ｿﾉﾀ)","pref_kanji":"三重県","city_kanji":"津市","town_kanji":"一志町八太（その他）","pref_roman":"MIE KEN","city_roman":"TSU SHI","town_roman":"ICHISHICHO HATA(SONOTA)"},"5152503":{"code":"24201","old_zip_code":"51525","zip_code":"5152503","pref_kana":"ﾐｴｹﾝ","city_kana":"ﾂｼ","town_kana":"ｲﾁｼﾁｮｳﾋｵｷ","pref_kanji":"三重県","city_kanji":"津市","town_kanji":"一志町日置","pref_roman":"MIE KEN","city_roman":"TSU SHI","town_roman":"ICHISHICHO HIOKI"},"5152517":{"code":"24201","old_zip_code":"51525","zip_code":"5152517","pref_kana":"ﾐｴｹﾝ","city_kana":"ﾂｼ","town_kana":"ｲﾁｼﾁｮｳﾐﾉﾘｶﾞｵｶ","pref_kanji":"三重県","city_kanji":"津市","town_kanji":"一志町みのりケ丘","pref_roman":"MIE KEN","city_roman":"TSU SHI","town_roman":"ICHISHICHO MINORIGAOKA"},"5152617":{"code":"24201","old_zip_code":"51526","zip_code":"5152617","pref_kana":"ﾐｴｹﾝ","city_kana":"ﾂｼ","town_kana":"ｸﾞﾘﾝﾀｳﾝｻｶｷﾊﾞﾗ","pref_kanji":"三重県","city_kanji":"津市","town_kanji":"グリンタウン榊原","pref_roman":"MIE KEN","city_roman":"TSU SHI","town_roman":"GURINTAUNSAKAKIBARA"},"5152605":{"code":"24201","old_zip_code":"51526","zip_code":"5152605","pref_kana":"ﾐｴｹﾝ","city_kana":"ﾂｼ","town_kana":"ﾊｸｻﾝﾀﾞｲ","pref_kanji":"三重県","city_kanji":"津市","town_kanji":"白山台","pref_roman":"MIE KEN","city_roman":"TSU SHI","town_roman":"HAKUSANDAI"},"5152614":{"code":"24201","old_zip_code":"51526","zip_code":"5152614","pref_kana":"ﾐｴｹﾝ","city_kana":"ﾂｼ","town_kana":"ﾊｸｻﾝﾁｮｳｲｾﾐ","pref_kanji":"三重県","city_kanji":"津市","town_kanji":"白山町伊勢見","pref_roman":"MIE KEN","city_roman":"TSU SHI","town_roman":"HAKUSANCHO ISEMI"},"5152616":{"code":"24201","old_zip_code":"51526","zip_code":"5152616","pref_kana":"ﾐｴｹﾝ","city_kana":"ﾂｼ","town_kana":"ﾊｸｻﾝﾁｮｳｲﾅｶｹ","pref_kanji":"三重県","city_kanji":"津市","town_kanji":"白山町稲垣","pref_roman":"MIE KEN","city_roman":"TSU SHI","town_roman":"HAKUSANCHO INAKAKE"},"5152604":{"code":"24201","old_zip_code":"51526","zip_code":"5152604","pref_kana":"ﾐｴｹﾝ","city_kana":"ﾂｼ","town_kana":"ﾊｸｻﾝﾁｮｳｵｶ","pref_kanji":"三重県","city_kanji":"津市","town_kanji":"白山町岡","pref_roman":"MIE KEN","city_roman":"TSU SHI","town_roman":"HAKUSANCHO OKA"},"5152624":{"code":"24201","old_zip_code":"51526","zip_code":"5152624","pref_kana":"ﾐｴｹﾝ","city_kana":"ﾂｼ","town_kana":"ﾊｸｻﾝﾁｮｳｶｲﾄ","pref_kanji":"三重県","city_kanji":"津市","town_kanji":"白山町垣内","pref_roman":"MIE KEN","city_roman":"TSU SHI","town_roman":"HAKUSANCHO KAITO"},"5152623":{"code":"24201","old_zip_code":"51526","zip_code":"5152623","pref_kana":"ﾐｴｹﾝ","city_kana":"ﾂｼ","town_kana":"ﾊｸｻﾝﾁｮｳｶﾐﾉﾑﾗ","pref_kanji":"三重県","city_kanji":"津市","town_kanji":"白山町上ノ村","pref_roman":"MIE KEN","city_roman":"TSU SHI","town_roman":"HAKUSANCHO KAMINOMURA"},"5152603":{"code":"24201","old_zip_code":"51526","zip_code":"5152603","pref_kana":"ﾐｴｹﾝ","city_kana":"ﾂｼ","town_kana":"ﾊｸｻﾝﾁｮｳｶﾜｸﾞﾁ","pref_kanji":"三重県","city_kanji":"津市","town_kanji":"白山町川口","pref_roman":"MIE KEN","city_roman":"TSU SHI","town_roman":"HAKUSANCHO KAWAGUCHI"},"5152621":{"code":"24201","old_zip_code":"51526","zip_code":"5152621","pref_kana":"ﾐｴｹﾝ","city_kana":"ﾂｼ","town_kana":"ﾊｸｻﾝﾁｮｳｻﾀﾞ","pref_kanji":"三重県","city_kanji":"津市","town_kanji":"白山町佐田","pref_roman":"MIE KEN","city_roman":"TSU SHI","town_roman":"HAKUSANCHO SADA"},"5152622":{"code":"24201","old_zip_code":"51526","zip_code":"5152622","pref_kana":"ﾐｴｹﾝ","city_kana":"ﾂｼ","town_kana":"ﾊｸｻﾝﾁｮｳﾅｶﾉﾑﾗ","pref_kanji":"三重県","city_kanji":"津市","town_kanji":"白山町中ノ村","pref_roman":"MIE KEN","city_roman":"TSU SHI","town_roman":"HAKUSANCHO NAKANOMURA"},"5152602":{"code":"24201","old_zip_code":"51526","zip_code":"5152602","pref_kana":"ﾐｴｹﾝ","city_kana":"ﾂｼ","town_kana":"ﾊｸｻﾝﾁｮｳﾆﾎﾝｷﾞ","pref_kanji":"三重県","city_kanji":"津市","town_kanji":"白山町二本木","pref_roman":"MIE KEN","city_roman":"TSU SHI","town_roman":"HAKUSANCHO NIHONGI"},"5152615":{"code":"24201","old_zip_code":"51526","zip_code":"5152615","pref_kana":"ﾐｴｹﾝ","city_kana":"ﾂｼ","town_kana":"ﾊｸｻﾝﾁｮｳﾊｯﾀｲﾉ","pref_kanji":"三重県","city_kanji":"津市","town_kanji":"白山町八対野","pref_roman":"MIE KEN","city_roman":"TSU SHI","town_roman":"HAKUSANCHO HATTAINO"},"5152612":{"code":"24201","old_zip_code":"51526","zip_code":"5152612","pref_kana":"ﾐｴｹﾝ","city_kana":"ﾂｼ","town_kana":"ﾊｸｻﾝﾁｮｳﾌﾙｲﾁ","pref_kanji":"三重県","city_kanji":"津市","town_kanji":"白山町古市","pref_roman":"MIE KEN","city_roman":"TSU SHI","town_roman":"HAKUSANCHO FURUICHI"},"5152601":{"code":"24201","old_zip_code":"51526","zip_code":"5152601","pref_kana":"ﾐｴｹﾝ","city_kana":"ﾂｼ","town_kana":"ﾊｸｻﾝﾁｮｳﾐﾂｶﾞﾉ","pref_kanji":"三重県","city_kanji":"津市","town_kanji":"白山町三ケ野","pref_roman":"MIE KEN","city_roman":"TSU SHI","town_roman":"HAKUSANCHO MITSUGANO"},"5152611":{"code":"24201","old_zip_code":"51526","zip_code":"5152611","pref_kana":"ﾐｴｹﾝ","city_kana":"ﾂｼ","town_kana":"ﾊｸｻﾝﾁｮｳﾐﾅﾐﾃﾞ","pref_kanji":"三重県","city_kanji":"津市","town_kanji":"白山町南出","pref_roman":"MIE KEN","city_roman":"TSU SHI","town_roman":"HAKUSANCHO MINAMIDE"},"5152613":{"code":"24201","old_zip_code":"51526","zip_code":"5152613","pref_kana":"ﾐｴｹﾝ","city_kana":"ﾂｼ","town_kana":"ﾊｸｻﾝﾁｮｳﾔﾏﾀﾞﾉ","pref_kanji":"三重県","city_kanji":"津市","town_kanji":"白山町山田野","pref_roman":"MIE KEN","city_roman":"TSU SHI","town_roman":"HAKUSANCHO YAMADANO"},"5152121":{"code":"24204","old_zip_code":"51521","zip_code":"5152121","pref_kana":"ﾐｴｹﾝ","city_kana":"ﾏﾂｻｶｼ","town_kana":"ｲﾁﾊﾞｼｮｳﾁｮｳ","pref_kanji":"三重県","city_kanji":"松阪市","town_kanji":"市場庄町","pref_roman":"MIE KEN","city_roman":"MATSUSAKA SHI","town_roman":"ICHIBASHOCHO"},"5152412":{"code":"24204","old_zip_code":"51524","zip_code":"5152412","pref_kana":"ﾐｴｹﾝ","city_kana":"ﾏﾂｻｶｼ","town_kana":"ｲﾌﾀﾁｮｳ","pref_kanji":"三重県","city_kanji":"松阪市","town_kanji":"飯福田町","pref_roman":"MIE KEN","city_roman":"MATSUSAKA SHI","town_roman":"IFUTACHO"},"5152413":{"code":"24204","old_zip_code":"51524","zip_code":"5152413","pref_kana":"ﾐｴｹﾝ","city_kana":"ﾏﾂｻｶｼ","town_kana":"ｳｼﾛﾔﾏﾁｮｳ","pref_kanji":"三重県","city_kanji":"松阪市","town_kanji":"後山町","pref_roman":"MIE KEN","city_roman":"MATSUSAKA SHI","town_roman":"USHIROYAMACHO"},"5152305":{"code":"24204","old_zip_code":"51523","zip_code":"5152305","pref_kana":"ﾐｴｹﾝ","city_kana":"ﾏﾂｻｶｼ","town_kana":"ｳﾚｼﾉｲﾁｼﾁｮｳ","pref_kanji":"三重県","city_kanji":"松阪市","town_kanji":"嬉野一志町","pref_roman":"MIE KEN","city_roman":"MATSUSAKA SHI","town_roman":"URESHINO ICHISHICHO"},"5152351":{"code":"24204","old_zip_code":"51523","zip_code":"5152351","pref_kana":"ﾐｴｹﾝ","city_kana":"ﾏﾂｻｶｼ","town_kana":"ｳﾚｼﾉｲﾉｳｴﾁｮｳ","pref_kanji":"三重県","city_kanji":"松阪市","town_kanji":"嬉野井之上町","pref_roman":"MIE KEN","city_roman":"MATSUSAKA SHI","town_roman":"URESHINO INOECHO"},"5152403":{"code":"24204","old_zip_code":"51524","zip_code":"5152403","pref_kana":"ﾐｴｹﾝ","city_kana":"ﾏﾂｻｶｼ","town_kana":"ｳﾚｼﾉｲﾜｸﾗﾁｮｳ","pref_kanji":"三重県","city_kanji":"松阪市","town_kanji":"嬉野岩倉町","pref_roman":"MIE KEN","city_roman":"MATSUSAKA SHI","town_roman":"URESHINO IWAKURACHO"},"5152356":{"code":"24204","old_zip_code":"51523","zip_code":"5152356","pref_kana":"ﾐｴｹﾝ","city_kana":"ﾏﾂｻｶｼ","town_kana":"ｳﾚｼﾉｳｴﾉﾁｮｳ","pref_kanji":"三重県","city_kanji":"松阪市","town_kanji":"嬉野上野町","pref_roman":"MIE KEN","city_roman":"MATSUSAKA SHI","town_roman":"URESHINO UENOCHO"},"5152405":{"code":"24204","old_zip_code":"51524","zip_code":"5152405","pref_kana":"ﾐｴｹﾝ","city_kana":"ﾏﾂｻｶｼ","town_kana":"ｳﾚｼﾉｵﾊﾗﾁｮｳ","pref_kanji":"三重県","city_kanji":"松阪市","town_kanji":"嬉野小原町","pref_roman":"MIE KEN","city_roman":"MATSUSAKA SHI","town_roman":"URESHINO OHARACHO"},"5152404":{"code":"24204","old_zip_code":"51524","zip_code":"5152404","pref_kana":"ﾐｴｹﾝ","city_kana":"ﾏﾂｻｶｼ","town_kana":"ｳﾚｼﾉｶﾐｵｶﾞﾜﾁｮｳ","pref_kanji":"三重県","city_kanji":"松阪市","town_kanji":"嬉野上小川町","pref_roman":"MIE KEN","city_roman":"MATSUSAKA SHI","town_roman":"URESHINO KAMIOGAWACHO"},"5152357":{"code":"24204","old_zip_code":"51523","zip_code":"5152357","pref_kana":"ﾐｴｹﾝ","city_kana":"ﾏﾂｻｶｼ","town_kana":"ｳﾚｼﾉｶﾐﾉｷﾁｮｳ","pref_kanji":"三重県","city_kanji":"松阪市","town_kanji":"嬉野神ノ木町","pref_roman":"MIE KEN","city_roman":"MATSUSAKA SHI","town_roman":"URESHINO KAMINOKICHO"},"5152401":{"code":"24204","old_zip_code":"51524","zip_code":"5152401","pref_kana":"ﾐｴｹﾝ","city_kana":"ﾏﾂｻｶｼ","town_kana":"ｳﾚｼﾉｶﾓﾀﾞﾁｮｳ","pref_kanji":"三重県","city_kanji":"松阪市","town_kanji":"嬉野釜生田町","pref_roman":"MIE KEN","city_roman":"MATSUSAKA SHI","town_roman":"URESHINO KAMODACHO"},"5152316":{"code":"24204","old_zip_code":"51523","zip_code":"5152316","pref_kana":"ﾐｴｹﾝ","city_kana":"ﾏﾂｻｶｼ","town_kana":"ｳﾚｼﾉｶﾜｷﾞﾀﾁｮｳ","pref_kanji":"三重県","city_kanji":"松阪市","town_kanji":"嬉野川北町","pref_roman":"MIE KEN","city_roman":"MATSUSAKA SHI","town_roman":"URESHINO KAWAGITACHO"},"5152313":{"code":"24204","old_zip_code":"51523","zip_code":"5152313","pref_kana":"ﾐｴｹﾝ","city_kana":"ﾏﾂｻｶｼ","town_kana":"ｳﾚｼﾉｶﾜﾗｺﾂｸﾘﾁｮｳ","pref_kanji":"三重県","city_kanji":"松阪市","town_kanji":"嬉野川原木造町","pref_roman":"MIE KEN","city_roman":"MATSUSAKA SHI","town_roman":"URESHINO KAWARAKOTSUKURICHO"},"5152311":{"code":"24204","old_zip_code":"51523","zip_code":"5152311","pref_kana":"ﾐｴｹﾝ","city_kana":"ﾏﾂｻｶｼ","town_kana":"ｳﾚｼﾉｸﾛﾀﾞﾁｮｳ","pref_kanji":"三重県","city_kanji":"松阪市","town_kanji":"嬉野黒田町","pref_roman":"MIE KEN","city_roman":"MATSUSAKA SHI","town_roman":"URESHINO KURODACHO"},"5152334":{"code":"24204","old_zip_code":"51523","zip_code":"5152334","pref_kana":"ﾐｴｹﾝ","city_kana":"ﾏﾂｻｶｼ","town_kana":"ｳﾚｼﾉｸﾛﾉﾁｮｳ","pref_kanji":"三重県","city_kanji":"松阪市","town_kanji":"嬉野黒野町","pref_roman":"MIE KEN","city_roman":"MATSUSAKA SHI","town_roman":"URESHINO KURONOCHO"},"5152406":{"code":"24204","old_zip_code":"51524","zip_code":"5152406","pref_kana":"ﾐｴｹﾝ","city_kana":"ﾏﾂｻｶｼ","town_kana":"ｳﾚｼﾉｺﾞｶﾞﾉﾁｮｳ","pref_kanji":"三重県","city_kanji":"松阪市","town_kanji":"嬉野合ケ野町","pref_roman":"MIE KEN","city_roman":"MATSUSAKA SHI","town_roman":"URESHINO GOGANOCHO"},"5152315":{"code":"24204","old_zip_code":"51523","zip_code":"5152315","pref_kana":"ﾐｴｹﾝ","city_kana":"ﾏﾂｻｶｼ","town_kana":"ｳﾚｼﾉｺﾑﾗﾁｮｳ","pref_kanji":"三重県","city_kanji":"松阪市","town_kanji":"嬉野小村町","pref_roman":"MIE KEN","city_roman":"MATSUSAKA SHI","town_roman":"URESHINO KOMURACHO"},"5152323":{"code":"24204","old_zip_code":"51523","zip_code":"5152323","pref_kana":"ﾐｴｹﾝ","city_kana":"ﾏﾂｻｶｼ","town_kana":"ｳﾚｼﾉｺﾞﾝｹﾞﾝﾏｴﾁｮｳ","pref_kanji":"三重県","city_kanji":"松阪市","town_kanji":"嬉野権現前町","pref_roman":"MIE KEN","city_roman":"MATSUSAKA SHI","town_roman":"URESHINO GONGEMMAECHO"},"5152335":{"code":"24204","old_zip_code":"51523","zip_code":"5152335","pref_kana":"ﾐｴｹﾝ","city_kana":"ﾏﾂｻｶｼ","town_kana":"ｳﾚｼﾉｻﾝｼﾞｮﾁｮｳ","pref_kanji":"三重県","city_kanji":"松阪市","town_kanji":"嬉野算所町","pref_roman":"MIE KEN","city_roman":"MATSUSAKA SHI","town_roman":"URESHINO SANJOCHO"},"5152301":{"code":"24204","old_zip_code":"51523","zip_code":"5152301","pref_kana":"ﾐｴｹﾝ","city_kana":"ﾏﾂｻｶｼ","town_kana":"ｳﾚｼﾉｼﾏﾀﾞﾁｮｳ","pref_kanji":"三重県","city_kanji":"松阪市","town_kanji":"嬉野島田町","pref_roman":"MIE KEN","city_roman":"MATSUSAKA SHI","town_roman":"URESHINO SHIMADACHO"},"5152354":{"code":"24204","old_zip_code":"51523","zip_code":"5152354","pref_kana":"ﾐｴｹﾝ","city_kana":"ﾏﾂｻｶｼ","town_kana":"ｳﾚｼﾉｼﾓﾉｼｮｳﾁｮｳ","pref_kanji":"三重県","city_kanji":"松阪市","town_kanji":"嬉野下之庄町","pref_roman":"MIE KEN","city_roman":"MATSUSAKA SHI","town_roman":"URESHINO SHIMONOSHOCHO"},"5152322":{"code":"24204","old_zip_code":"51523","zip_code":"5152322","pref_kana":"ﾐｴｹﾝ","city_kana":"ﾏﾂｻｶｼ","town_kana":"ｳﾚｼﾉｽｶﾁｮｳ","pref_kanji":"三重県","city_kanji":"松阪市","town_kanji":"嬉野須賀町","pref_roman":"MIE KEN","city_roman":"MATSUSAKA SHI","town_roman":"URESHINO SUKACHO"},"5152331":{"code":"24204","old_zip_code":"51523","zip_code":"5152331","pref_kana":"ﾐｴｹﾝ","city_kana":"ﾏﾂｻｶｼ","town_kana":"ｳﾚｼﾉｽｶﾘｮｳﾁｮｳ","pref_kanji":"三重県","city_kanji":"松阪市","town_kanji":"嬉野須賀領町","pref_roman":"MIE KEN","city_roman":"MATSUSAKA SHI","town_roman":"URESHINO SUKARYOCHO"},"5152409":{"code":"24204","old_zip_code":"51524","zip_code":"5152409","pref_kana":"ﾐｴｹﾝ","city_kana":"ﾏﾂｻｶｼ","town_kana":"ｳﾚｼﾉﾀｷﾉｶﾞﾜﾁｮｳ","pref_kanji":"三重県","city_kanji":"松阪市","town_kanji":"嬉野滝之川町","pref_roman":"MIE KEN","city_roman":"MATSUSAKA SHI","town_roman":"URESHINO TAKINOGAWACHO"},"5152333":{"code":"24204","old_zip_code":"51523","zip_code":"5152333","pref_kana":"ﾐｴｹﾝ","city_kana":"ﾏﾂｻｶｼ","town_kana":"ｳﾚｼﾉﾀﾑﾗﾁｮｳ","pref_kanji":"三重県","city_kanji":"松阪市","town_kanji":"嬉野田村町","pref_roman":"MIE KEN","city_roman":"MATSUSAKA SHI","town_roman":"URESHINO TAMURACHO"},"5152332":{"code":"24204","old_zip_code":"51523","zip_code":"5152332","pref_kana":"ﾐｴｹﾝ","city_kana":"ﾏﾂｻｶｼ","town_kana":"ｳﾚｼﾉﾂﾔｼﾞｮｳﾁｮｳ","pref_kanji":"三重県","city_kanji":"松阪市","town_kanji":"嬉野津屋城町","pref_roman":"MIE KEN","city_roman":"MATSUSAKA SHI","town_roman":"URESHINO TSUYAJOCHO"},"5152302":{"code":"24204","old_zip_code":"51523","zip_code":"5152302","pref_kana":"ﾐｴｹﾝ","city_kana":"ﾏﾂｻｶｼ","town_kana":"ｳﾚｼﾉﾃﾝｹﾞｴｼﾞﾁｮｳ","pref_kanji":"三重県","city_kanji":"松阪市","town_kanji":"嬉野天花寺町","pref_roman":"MIE KEN","city_roman":"MATSUSAKA SHI","town_roman":"URESHINO TENGEEJICHO"},"5152325":{"code":"24204","old_zip_code":"51523","zip_code":"5152325","pref_kana":"ﾐｴｹﾝ","city_kana":"ﾏﾂｻｶｼ","town_kana":"ｳﾚｼﾉﾅｶｶﾞﾜｼﾝﾏﾁ","pref_kanji":"三重県","city_kanji":"松阪市","town_kanji":"嬉野中川新町","pref_roman":"MIE KEN","city_roman":"MATSUSAKA SHI","town_roman":"URESHINO NAKAGAWASHIMMACHI"},"5152321":{"code":"24204","old_zip_code":"51523","zip_code":"5152321","pref_kana":"ﾐｴｹﾝ","city_kana":"ﾏﾂｻｶｼ","town_kana":"ｳﾚｼﾉﾅｶｶﾞﾜﾁｮｳ","pref_kanji":"三重県","city_kanji":"松阪市","town_kanji":"嬉野中川町","pref_roman":"MIE KEN","city_roman":"MATSUSAKA SHI","town_roman":"URESHINO NAKAGAWACHO"},"5152314":{"code":"24204","old_zip_code":"51523","zip_code":"5152314","pref_kana":"ﾐｴｹﾝ","city_kana":"ﾏﾂｻｶｼ","town_kana":"ｳﾚｼﾉﾆﾜﾉｼｮｳﾁｮｳ","pref_kanji":"三重県","city_kanji":"松阪市","town_kanji":"嬉野新屋庄町","pref_roman":"MIE KEN","city_roman":"MATSUSAKA SHI","town_roman":"URESHINO NIWANOSHOCHO"},"5152317":{"code":"24204","old_zip_code":"51523","zip_code":"5152317","pref_kana":"ﾐｴｹﾝ","city_kana":"ﾏﾂｻｶｼ","town_kana":"ｳﾚｼﾉﾉﾀﾞﾁｮｳ","pref_kanji":"三重県","city_kanji":"松阪市","town_kanji":"嬉野野田町","pref_roman":"MIE KEN","city_roman":"MATSUSAKA SHI","town_roman":"URESHINO NODACHO"},"5152352":{"code":"24204","old_zip_code":"51523","zip_code":"5152352","pref_kana":"ﾐｴｹﾝ","city_kana":"ﾏﾂｻｶｼ","town_kana":"ｳﾚｼﾉﾊｯﾀﾁｮｳ","pref_kanji":"三重県","city_kanji":"松阪市","town_kanji":"嬉野八田町","pref_roman":"MIE KEN","city_roman":"MATSUSAKA SHI","town_roman":"URESHINO HATTACHO"},"5152304":{"code":"24204","old_zip_code":"51523","zip_code":"5152304","pref_kana":"ﾐｴｹﾝ","city_kana":"ﾏﾂｻｶｼ","town_kana":"ｳﾚｼﾉﾋﾛﾁｮｳ","pref_kanji":"三重県","city_kanji":"松阪市","town_kanji":"嬉野平生町","pref_roman":"MIE KEN","city_roman":"MATSUSAKA SHI","town_roman":"URESHINO HIROCHO"},"5152353":{"code":"24204","old_zip_code":"51523","zip_code":"5152353","pref_kana":"ﾐｴｹﾝ","city_kana":"ﾏﾂｻｶｼ","town_kana":"ｳﾚｼﾉﾎﾘﾉｳﾁﾁｮｳ","pref_kanji":"三重県","city_kanji":"松阪市","town_kanji":"嬉野堀之内町","pref_roman":"MIE KEN","city_roman":"MATSUSAKA SHI","town_roman":"URESHINO HORINOCHICHO"},"5152312":{"code":"24204","old_zip_code":"51523","zip_code":"5152312","pref_kana":"ﾐｴｹﾝ","city_kana":"ﾏﾂｻｶｼ","town_kana":"ｳﾚｼﾉﾐﾅｶﾞﾁｮｳ","pref_kanji":"三重県","city_kanji":"松阪市","town_kanji":"嬉野見永町","pref_roman":"MIE KEN","city_roman":"MATSUSAKA SHI","town_roman":"URESHINO MINAGACHO"},"5152303":{"code":"24204","old_zip_code":"51523","zip_code":"5152303","pref_kana":"ﾐｴｹﾝ","city_kana":"ﾏﾂｻｶｼ","town_kana":"ｳﾚｼﾉﾐﾔｺﾁｮｳ","pref_kanji":"三重県","city_kanji":"松阪市","town_kanji":"嬉野宮古町","pref_roman":"MIE KEN","city_roman":"MATSUSAKA SHI","town_roman":"URESHINO MIYAKOCHO"},"5152408":{"code":"24204","old_zip_code":"51524","zip_code":"5152408","pref_kana":"ﾐｴｹﾝ","city_kana":"ﾏﾂｻｶｼ","town_kana":"ｳﾚｼﾉﾐﾔﾉﾁｮｳ","pref_kanji":"三重県","city_kanji":"松阪市","town_kanji":"嬉野宮野町","pref_roman":"MIE KEN","city_roman":"MATSUSAKA SHI","town_roman":"URESHINO MIYANOCHO"},"5152402":{"code":"24204","old_zip_code":"51524","zip_code":"5152402","pref_kana":"ﾐｴｹﾝ","city_kana":"ﾏﾂｻｶｼ","town_kana":"ｳﾚｼﾉﾓﾘﾓﾄﾁｮｳ","pref_kanji":"三重県","city_kanji":"松阪市","town_kanji":"嬉野森本町","pref_roman":"MIE KEN","city_roman":"MATSUSAKA SHI","town_roman":"URESHINO MORIMOTOCHO"},"5152407":{"code":"24204","old_zip_code":"51524","zip_code":"5152407","pref_kana":"ﾐｴｹﾝ","city_kana":"ﾏﾂｻｶｼ","town_kana":"ｳﾚｼﾉﾔｵﾛｼﾁｮｳ","pref_kanji":"三重県","city_kanji":"松阪市","town_kanji":"嬉野矢下町","pref_roman":"MIE KEN","city_roman":"MATSUSAKA SHI","town_roman":"URESHINO YAOROSHICHO"},"5152355":{"code":"24204","old_zip_code":"51523","zip_code":"5152355","pref_kana":"ﾐｴｹﾝ","city_kana":"ﾏﾂｻｶｼ","town_kana":"ｳﾚｼﾉﾔｸｵｳｼﾞﾁｮｳ","pref_kanji":"三重県","city_kanji":"松阪市","town_kanji":"嬉野薬王寺町","pref_roman":"MIE KEN","city_roman":"MATSUSAKA SHI","town_roman":"URESHINO YAKUOJICHO"},"5152324":{"code":"24204","old_zip_code":"51523","zip_code":"5152324","pref_kana":"ﾐｴｹﾝ","city_kana":"ﾏﾂｻｶｼ","town_kana":"ｳﾚｼﾉﾁｮｳ","pref_kanji":"三重県","city_kanji":"松阪市","town_kanji":"嬉野町","pref_roman":"MIE KEN","city_roman":"MATSUSAKA SHI","town_roman":"URESHINOCHO"},"5152342":{"code":"24204","old_zip_code":"51523","zip_code":"5152342","pref_kana":"ﾐｴｹﾝ","city_kana":"ﾏﾂｻｶｼ","town_kana":"ｵｵｱｻﾞｶﾁｮｳ","pref_kanji":"三重県","city_kanji":"松阪市","town_kanji":"大阿坂町","pref_roman":"MIE KEN","city_roman":"MATSUSAKA SHI","town_roman":"OAZAKACHO"},"5152341":{"code":"24204","old_zip_code":"51523","zip_code":"5152341","pref_kana":"ﾐｴｹﾝ","city_kana":"ﾏﾂｻｶｼ","town_kana":"ｵｵﾉﾁｮｳ","pref_kanji":"三重県","city_kanji":"松阪市","town_kanji":"小野町","pref_roman":"MIE KEN","city_roman":"MATSUSAKA SHI","town_roman":"ONOCHO"},"5152114":{"code":"24204","old_zip_code":"51521","zip_code":"5152114","pref_kana":"ﾐｴｹﾝ","city_kana":"ﾏﾂｻｶｼ","town_kana":"ｵﾂﾞﾁｮｳ","pref_kanji":"三重県","city_kanji":"松阪市","town_kanji":"小津町","pref_roman":"MIE KEN","city_roman":"MATSUSAKA SHI","town_roman":"OZUCHO"},"5152109":{"code":"24204","old_zip_code":"51521","zip_code":"5152109","pref_kana":"ﾐｴｹﾝ","city_kana":"ﾏﾂｻｶｼ","town_kana":"ｵﾉｴﾁｮｳ","pref_kanji":"三重県","city_kanji":"松阪市","town_kanji":"小野江町","pref_roman":"MIE KEN","city_roman":"MATSUSAKA SHI","town_roman":"ONOECHO"},"5152103":{"code":"24204","old_zip_code":"51521","zip_code":"5152103","pref_kana":"ﾐｴｹﾝ","city_kana":"ﾏﾂｻｶｼ","town_kana":"ｶｻﾏﾂﾁｮｳ","pref_kanji":"三重県","city_kanji":"松阪市","town_kanji":"笠松町","pref_roman":"MIE KEN","city_roman":"MATSUSAKA SHI","town_roman":"KASAMATSUCHO"},"5152123":{"code":"24204","old_zip_code":"51521","zip_code":"5152123","pref_kana":"ﾐｴｹﾝ","city_kana":"ﾏﾂｻｶｼ","town_kana":"ｶﾐﾉｼｮｳﾁｮｳ","pref_kanji":"三重県","city_kanji":"松阪市","town_kanji":"上ノ庄町","pref_roman":"MIE KEN","city_roman":"MATSUSAKA SHI","town_roman":"KAMINOSHOCHO"},"5152113":{"code":"24204","old_zip_code":"51521","zip_code":"5152113","pref_kana":"ﾐｴｹﾝ","city_kana":"ﾏﾂｻｶｼ","town_kana":"ｷﾀﾑﾗｼﾝﾃﾞﾝﾁｮｳ","pref_kanji":"三重県","city_kanji":"松阪市","town_kanji":"喜多村新田町","pref_roman":"MIE KEN","city_roman":"MATSUSAKA SHI","town_roman":"KITAMURASHINDENCHO"},"5152122":{"code":"24204","old_zip_code":"51521","zip_code":"5152122","pref_kana":"ﾐｴｹﾝ","city_kana":"ﾏﾂｻｶｼ","town_kana":"ｸﾒﾁｮｳ","pref_kanji":"三重県","city_kanji":"松阪市","town_kanji":"久米町","pref_roman":"MIE KEN","city_roman":"MATSUSAKA SHI","town_roman":"KUMECHO"},"5152343":{"code":"24204","old_zip_code":"51523","zip_code":"5152343","pref_kana":"ﾐｴｹﾝ","city_kana":"ﾏﾂｻｶｼ","town_kana":"ｺｱｻﾞｶﾁｮｳ","pref_kanji":"三重県","city_kanji":"松阪市","town_kanji":"小阿坂町","pref_roman":"MIE KEN","city_roman":"MATSUSAKA SHI","town_roman":"KOAZAKACHO"},"5152102":{"code":"24204","old_zip_code":"51521","zip_code":"5152102","pref_kana":"ﾐｴｹﾝ","city_kana":"ﾏﾂｻｶｼ","town_kana":"ｺﾞﾇｼﾁｮｳ","pref_kanji":"三重県","city_kanji":"松阪市","town_kanji":"五主町","pref_roman":"MIE KEN","city_roman":"MATSUSAKA SHI","town_roman":"GONUSHICHO"},"5152104":{"code":"24204","old_zip_code":"51521","zip_code":"5152104","pref_kana":"ﾐｴｹﾝ","city_kana":"ﾏﾂｻｶｼ","town_kana":"ｺﾌﾞﾅｴﾁｮｳ","pref_kanji":"三重県","city_kanji":"松阪市","town_kanji":"小舟江町","pref_roman":"MIE KEN","city_roman":"MATSUSAKA SHI","town_roman":"KOBUNAECHO"},"5152112":{"code":"24204","old_zip_code":"51521","zip_code":"5152112","pref_kana":"ﾐｴｹﾝ","city_kana":"ﾏﾂｻｶｼ","town_kana":"ｿﾊﾗﾁｮｳ","pref_kanji":"三重県","city_kanji":"松阪市","town_kanji":"曽原町","pref_roman":"MIE KEN","city_roman":"MATSUSAKA SHI","town_roman":"SOHARACHO"},"5152124":{"code":"24204","old_zip_code":"51521","zip_code":"5152124","pref_kana":"ﾐｴｹﾝ","city_kana":"ﾏﾂｻｶｼ","town_kana":"ﾅｶﾉｼｮｳﾁｮｳ","pref_kanji":"三重県","city_kanji":"松阪市","town_kanji":"中ノ庄町","pref_roman":"MIE KEN","city_roman":"MATSUSAKA SHI","town_roman":"NAKANOSHOCHO"},"5152111":{"code":"24204","old_zip_code":"51521","zip_code":"5152111","pref_kana":"ﾐｴｹﾝ","city_kana":"ﾏﾂｻｶｼ","town_kana":"ﾅｶﾊﾞﾔｼﾁｮｳ","pref_kanji":"三重県","city_kanji":"松阪市","town_kanji":"中林町","pref_roman":"MIE KEN","city_roman":"MATSUSAKA SHI","town_roman":"NAKABAYASHICHO"},"5152115":{"code":"24204","old_zip_code":"51521","zip_code":"5152115","pref_kana":"ﾐｴｹﾝ","city_kana":"ﾏﾂｻｶｼ","town_kana":"ﾅｶﾐﾁﾁｮｳ","pref_kanji":"三重県","city_kanji":"松阪市","town_kanji":"中道町","pref_roman":"MIE KEN","city_roman":"MATSUSAKA SHI","town_roman":"NAKAMICHICHO"},"5152106":{"code":"24204","old_zip_code":"51521","zip_code":"5152106","pref_kana":"ﾐｴｹﾝ","city_kana":"ﾏﾂｻｶｼ","town_kana":"ﾆｼﾋﾙﾁｮｳ","pref_kanji":"三重県","city_kanji":"松阪市","town_kanji":"西肥留町","pref_roman":"MIE KEN","city_roman":"MATSUSAKA SHI","town_roman":"NISHIHIRUCHO"},"5152108":{"code":"24204","old_zip_code":"51521","zip_code":"5152108","pref_kana":"ﾐｴｹﾝ","city_kana":"ﾏﾂｻｶｼ","town_kana":"ﾊﾀﾞﾒﾁｮｳ","pref_kanji":"三重県","city_kanji":"松阪市","town_kanji":"甚目町","pref_roman":"MIE KEN","city_roman":"MATSUSAKA SHI","town_roman":"HADAMECHO"},"5152105":{"code":"24204","old_zip_code":"51521","zip_code":"5152105","pref_kana":"ﾐｴｹﾝ","city_kana":"ﾏﾂｻｶｼ","town_kana":"ﾋﾙﾁｮｳ","pref_kanji":"三重県","city_kanji":"松阪市","town_kanji":"肥留町","pref_roman":"MIE KEN","city_roman":"MATSUSAKA SHI","town_roman":"HIRUCHO"},"5152101":{"code":"24204","old_zip_code":"51521","zip_code":"5152101","pref_kana":"ﾐｴｹﾝ","city_kana":"ﾏﾂｻｶｼ","town_kana":"ﾎｼｱｲﾁｮｳ","pref_kanji":"三重県","city_kanji":"松阪市","town_kanji":"星合町","pref_roman":"MIE KEN","city_roman":"MATSUSAKA SHI","town_roman":"HOSHIAICHO"},"5152107":{"code":"24204","old_zip_code":"51521","zip_code":"5152107","pref_kana":"ﾐｴｹﾝ","city_kana":"ﾏﾂｻｶｼ","town_kana":"ﾏｲﾃﾞﾁｮｳ","pref_kanji":"三重県","city_kanji":"松阪市","town_kanji":"舞出町","pref_roman":"MIE KEN","city_roman":"MATSUSAKA SHI","town_roman":"MAIDECHO"},"5152133":{"code":"24204","old_zip_code":"51521","zip_code":"5152133","pref_kana":"ﾐｴｹﾝ","city_kana":"ﾏﾂｻｶｼ","town_kana":"ﾏﾂｶﾞｼﾏﾁｮｳ","pref_kanji":"三重県","city_kanji":"松阪市","town_kanji":"松ケ島町","pref_roman":"MIE KEN","city_roman":"MATSUSAKA SHI","town_roman":"MATSUGASHIMACHO"},"5152132":{"code":"24204","old_zip_code":"51521","zip_code":"5152132","pref_kana":"ﾐｴｹﾝ","city_kana":"ﾏﾂｻｶｼ","town_kana":"ﾏﾂｻｷｳﾗﾁｮｳ","pref_kanji":"三重県","city_kanji":"松阪市","town_kanji":"松崎浦町","pref_roman":"MIE KEN","city_roman":"MATSUSAKA SHI","town_roman":"MATSUSAKIURACHO"},"5152344":{"code":"24204","old_zip_code":"51523","zip_code":"5152344","pref_kana":"ﾐｴｹﾝ","city_kana":"ﾏﾂｻｶｼ","town_kana":"ﾐﾉﾀﾞﾁｮｳ","pref_kanji":"三重県","city_kanji":"松阪市","town_kanji":"美濃田町","pref_roman":"MIE KEN","city_roman":"MATSUSAKA SHI","town_roman":"MINODACHO"},"5152414":{"code":"24204","old_zip_code":"51524","zip_code":"5152414","pref_kana":"ﾐｴｹﾝ","city_kana":"ﾏﾂｻｶｼ","town_kana":"ﾕﾉﾊﾗﾁｮｳ","pref_kanji":"三重県","city_kanji":"松阪市","town_kanji":"柚原町","pref_roman":"MIE KEN","city_roman":"MATSUSAKA SHI","town_roman":"YUNOHARACHO"},"5152411":{"code":"24204","old_zip_code":"51524","zip_code":"5152411","pref_kana":"ﾐｴｹﾝ","city_kana":"ﾏﾂｻｶｼ","town_kana":"ﾖﾊﾗﾁｮｳ","pref_kanji":"三重県","city_kanji":"松阪市","town_kanji":"与原町","pref_roman":"MIE KEN","city_roman":"MATSUSAKA SHI","town_roman":"YOHARACHO"},"5152131":{"code":"24204","old_zip_code":"51521","zip_code":"5152131","pref_kana":"ﾐｴｹﾝ","city_kana":"ﾏﾂｻｶｼ","town_kana":"ﾛｯｹﾝﾁｮｳ","pref_kanji":"三重県","city_kanji":"松阪市","town_kanji":"六軒町","pref_roman":"MIE KEN","city_roman":"MATSUSAKA SHI","town_roman":"ROKKENCHO"}}
